{"nc":64,"clips":[{"node":{"durationSeconds":28,"videoOffsetSeconds":510,"viewCount":15},"cursor":null},{"node":{"durationSeconds":26,"videoOffsetSeconds":888,"viewCount":1},"cursor":null},{"node":{"durationSeconds":30,"videoOffsetSeconds":890,"viewCount":5},"cursor":null},{"node":{"durationSeconds":26,"videoOffsetSeconds":894,"viewCount":9},"cursor":null},{"node":{"durationSeconds":26,"videoOffsetSeconds":895,"viewCount":11},"cursor":null},{"node":{"durationSeconds":26,"videoOffsetSeconds":896,"viewCount":3},"cursor":null},{"node":{"durationSeconds":30,"videoOffsetSeconds":898,"viewCount":1},"cursor":null},{"node":{"durationSeconds":30,"videoOffsetSeconds":900,"viewCount":1},"cursor":null},{"node":{"durationSeconds":9,"videoOffsetSeconds":912,"viewCount":117},"cursor":null},{"node":{"durationSeconds":28,"videoOffsetSeconds":926,"viewCount":25},"cursor":null},{"node":{"durationSeconds":30,"videoOffsetSeconds":970,"viewCount":5},"cursor":null},{"node":{"durationSeconds":26,"videoOffsetSeconds":1022,"viewCount":5},"cursor":null},{"node":{"durationSeconds":28,"videoOffsetSeconds":1574,"viewCount":13},"cursor":null},{"node":{"durationSeconds":9,"videoOffsetSeconds":1706,"viewCount":147},"cursor":null},{"node":{"durationSeconds":30,"videoOffsetSeconds":2040,"viewCount":11},"cursor":null},{"node":{"durationSeconds":26,"videoOffsetSeconds":2060,"viewCount":73},"cursor":null},{"node":{"durationSeconds":30,"videoOffsetSeconds":2240,"viewCount":1},"cursor":null},{"node":{"durationSeconds":26,"videoOffsetSeconds":2340,"viewCount":9},"cursor":null},{"node":{"durationSeconds":28,"videoOffsetSeconds":2444,"viewCount":55},"cursor":null},{"node":{"durationSeconds":28,"videoOffsetSeconds":2644,"viewCount":43},"cursor":null},{"node":{"durationSeconds":26,"videoOffsetSeconds":2692,"viewCount":349},"cursor":null},{"node":{"durationSeconds":30,"videoOffsetSeconds":2890,"viewCount":17},"cursor":null},{"node":{"durationSeconds":30,"videoOffsetSeconds":3068,"viewCount":83},"cursor":null},{"node":{"durationSeconds":26,"videoOffsetSeconds":3106,"viewCount":828},"cursor":null},{"node":{"durationSeconds":26,"videoOffsetSeconds":3254,"viewCount":87},"cursor":null},{"node":{"durationSeconds":26,"videoOffsetSeconds":3294,"viewCount":11},"cursor":null},{"node":{"durationSeconds":15,"videoOffsetSeconds":3652,"viewCount":1148},"cursor":null},{"node":{"durationSeconds":30,"videoOffsetSeconds":3660,"viewCount":11},"cursor":null},{"node":{"durationSeconds":26,"videoOffsetSeconds":3942,"viewCount":15},"cursor":null},{"node":{"durationSeconds":28,"videoOffsetSeconds":4510,"viewCount":43},"cursor":null},{"node":{"durationSeconds":28,"videoOffsetSeconds":4614,"viewCount":3},"cursor":null},{"node":{"durationSeconds":26,"videoOffsetSeconds":4712,"viewCount":7},"cursor":null},{"node":{"durationSeconds":30,"videoOffsetSeconds":5140,"viewCount":3},"cursor":null},{"node":{"durationSeconds":30,"videoOffsetSeconds":5144,"viewCount":169},"cursor":null},{"node":{"durationSeconds":26,"videoOffsetSeconds":5280,"viewCount":5},"cursor":null},{"node":{"durationSeconds":26,"videoOffsetSeconds":5466,"viewCount":3},"cursor":null},{"node":{"durationSeconds":26,"videoOffsetSeconds":5836,"viewCount":3},"cursor":null},{"node":{"durationSeconds":26,"videoOffsetSeconds":6020,"viewCount":11},"cursor":null},{"node":{"durationSeconds":30,"videoOffsetSeconds":6198,"viewCount":233},"cursor":null},{"node":{"durationSeconds":30,"videoOffsetSeconds":6250,"viewCount":19},"cursor":null},{"node":{"durationSeconds":26,"videoOffsetSeconds":6400,"viewCount":21},"cursor":null},{"node":{"durationSeconds":26,"videoOffsetSeconds":6418,"viewCount":3},"cursor":null},{"node":{"durationSeconds":30,"videoOffsetSeconds":6900,"viewCount":25},"cursor":null},{"node":{"durationSeconds":30,"videoOffsetSeconds":7224,"viewCount":13},"cursor":null},{"node":{"durationSeconds":26,"videoOffsetSeconds":7360,"viewCount":3},"cursor":null},{"node":{"durationSeconds":28,"videoOffsetSeconds":7958,"viewCount":33},"cursor":null},{"node":{"durationSeconds":30,"videoOffsetSeconds":7976,"viewCount":53},"cursor":null},{"node":{"durationSeconds":26,"videoOffsetSeconds":8110,"viewCount":3},"cursor":null},{"node":{"durationSeconds":26,"videoOffsetSeconds":8110,"viewCount":9},"cursor":null},{"node":{"durationSeconds":28,"videoOffsetSeconds":8114,"viewCount":5},"cursor":null},{"node":{"durationSeconds":26,"videoOffsetSeconds":8120,"viewCount":5},"cursor":null},{"node":{"durationSeconds":30,"videoOffsetSeconds":8122,"viewCount":5},"cursor":null},{"node":{"durationSeconds":26,"videoOffsetSeconds":8126,"viewCount":175},"cursor":null},{"node":{"durationSeconds":26,"videoOffsetSeconds":8126,"viewCount":3},"cursor":null},{"node":{"durationSeconds":28,"videoOffsetSeconds":8138,"viewCount":1},"cursor":null},{"node":{"durationSeconds":26,"videoOffsetSeconds":8154,"viewCount":21},"cursor":null},{"node":{"durationSeconds":26,"videoOffsetSeconds":8154,"viewCount":1},"cursor":null},{"node":{"durationSeconds":30,"videoOffsetSeconds":8500,"viewCount":9},"cursor":null},{"node":{"durationSeconds":26,"videoOffsetSeconds":8762,"viewCount":3},"cursor":null},{"node":{"durationSeconds":28,"videoOffsetSeconds":8792,"viewCount":21},"cursor":null},{"node":{"durationSeconds":30,"videoOffsetSeconds":9120,"viewCount":1},"cursor":null},{"node":{"durationSeconds":28,"videoOffsetSeconds":9138,"viewCount":9},"cursor":null},{"node":{"durationSeconds":26,"videoOffsetSeconds":9168,"viewCount":3},"cursor":null},{"node":{"durationSeconds":30,"videoOffsetSeconds":9284,"viewCount":9},"cursor":null}],"url":{"quality":"Audio Only","resolution":null,"url":"https://dqrpb9wgowsf5.cloudfront.net/b412ca7f656d839214b5_ariasaki_40948271403_1657067153/audio_only/index-dvr.m3u8"},"len":9806}