{"nc":11,"clips":[{"node":{"durationSeconds":30,"videoOffsetSeconds":6626,"viewCount":13},"cursor":null},{"node":{"durationSeconds":30,"videoOffsetSeconds":6758,"viewCount":5},"cursor":null},{"node":{"durationSeconds":55,"videoOffsetSeconds":6760,"viewCount":105},"cursor":null},{"node":{"durationSeconds":26,"videoOffsetSeconds":13678,"viewCount":9},"cursor":null},{"node":{"durationSeconds":28,"videoOffsetSeconds":14978,"viewCount":27},"cursor":null},{"node":{"durationSeconds":28,"videoOffsetSeconds":18437,"viewCount":11},"cursor":null},{"node":{"durationSeconds":53,"videoOffsetSeconds":35542,"viewCount":5},"cursor":null},{"node":{"durationSeconds":30,"videoOffsetSeconds":41412,"viewCount":1},"cursor":null},{"node":{"durationSeconds":28,"videoOffsetSeconds":49348,"viewCount":3},"cursor":null},{"node":{"durationSeconds":28,"videoOffsetSeconds":61996,"viewCount":1},"cursor":null},{"node":{"durationSeconds":26,"videoOffsetSeconds":69556,"viewCount":3},"cursor":null}],"url":{"quality":"Audio Only","resolution":null,"url":"https://d1mhjrowxxagfy.cloudfront.net/ca9fad18af434c2e30ae_daljjang__39473089815_1657346525/audio_only/index-muted-81GAWI1D5O.m3u8"},"len":87176}