{"nc":217,"clips":[{"node":{"durationSeconds":30,"videoOffsetSeconds":0,"viewCount":1},"cursor":null},{"node":{"durationSeconds":10,"videoOffsetSeconds":0,"viewCount":1},"cursor":null},{"node":{"durationSeconds":10,"videoOffsetSeconds":0,"viewCount":1},"cursor":null},{"node":{"durationSeconds":10,"videoOffsetSeconds":0,"viewCount":1},"cursor":null},{"node":{"durationSeconds":10,"videoOffsetSeconds":0,"viewCount":1},"cursor":null},{"node":{"durationSeconds":10,"videoOffsetSeconds":0,"viewCount":1},"cursor":null},{"node":{"durationSeconds":10,"videoOffsetSeconds":0,"viewCount":1},"cursor":null},{"node":{"durationSeconds":10,"videoOffsetSeconds":0,"viewCount":1},"cursor":null},{"node":{"durationSeconds":20,"videoOffsetSeconds":0,"viewCount":1},"cursor":null},{"node":{"durationSeconds":10,"videoOffsetSeconds":0,"viewCount":1},"cursor":null},{"node":{"durationSeconds":20,"videoOffsetSeconds":0,"viewCount":1},"cursor":null},{"node":{"durationSeconds":10,"videoOffsetSeconds":0,"viewCount":1},"cursor":null},{"node":{"durationSeconds":30,"videoOffsetSeconds":0,"viewCount":1},"cursor":null},{"node":{"durationSeconds":10,"videoOffsetSeconds":0,"viewCount":1},"cursor":null},{"node":{"durationSeconds":30,"videoOffsetSeconds":0,"viewCount":1},"cursor":null},{"node":{"durationSeconds":10,"videoOffsetSeconds":0,"viewCount":1},"cursor":null},{"node":{"durationSeconds":10,"videoOffsetSeconds":0,"viewCount":1},"cursor":null},{"node":{"durationSeconds":30,"videoOffsetSeconds":10,"viewCount":1},"cursor":null},{"node":{"durationSeconds":30,"videoOffsetSeconds":10,"viewCount":1},"cursor":null},{"node":{"durationSeconds":26,"videoOffsetSeconds":12,"viewCount":1},"cursor":null},{"node":{"durationSeconds":30,"videoOffsetSeconds":20,"viewCount":1},"cursor":null},{"node":{"durationSeconds":30,"videoOffsetSeconds":24,"viewCount":1},"cursor":null},{"node":{"durationSeconds":30,"videoOffsetSeconds":30,"viewCount":1},"cursor":null},{"node":{"durationSeconds":30,"videoOffsetSeconds":40,"viewCount":1},"cursor":null},{"node":{"durationSeconds":30,"videoOffsetSeconds":40,"viewCount":1},"cursor":null},{"node":{"durationSeconds":30,"videoOffsetSeconds":40,"viewCount":1},"cursor":null},{"node":{"durationSeconds":28,"videoOffsetSeconds":58,"viewCount":1},"cursor":null},{"node":{"durationSeconds":28,"videoOffsetSeconds":58,"viewCount":1},"cursor":null},{"node":{"durationSeconds":30,"videoOffsetSeconds":70,"viewCount":1},"cursor":null},{"node":{"durationSeconds":30,"videoOffsetSeconds":80,"viewCount":7},"cursor":null},{"node":{"durationSeconds":30,"videoOffsetSeconds":80,"viewCount":1},"cursor":null},{"node":{"durationSeconds":30,"videoOffsetSeconds":90,"viewCount":1},"cursor":null},{"node":{"durationSeconds":28,"videoOffsetSeconds":130,"viewCount":5},"cursor":null},{"node":{"durationSeconds":30,"videoOffsetSeconds":130,"viewCount":1},"cursor":null},{"node":{"durationSeconds":30,"videoOffsetSeconds":150,"viewCount":29},"cursor":null},{"node":{"durationSeconds":30,"videoOffsetSeconds":150,"viewCount":1},"cursor":null},{"node":{"durationSeconds":30,"videoOffsetSeconds":170,"viewCount":1},"cursor":null},{"node":{"durationSeconds":26,"videoOffsetSeconds":210,"viewCount":3},"cursor":null},{"node":{"durationSeconds":30,"videoOffsetSeconds":234,"viewCount":1},"cursor":null},{"node":{"durationSeconds":26,"videoOffsetSeconds":242,"viewCount":1},"cursor":null},{"node":{"durationSeconds":28,"videoOffsetSeconds":254,"viewCount":3},"cursor":null},{"node":{"durationSeconds":30,"videoOffsetSeconds":260,"viewCount":1},"cursor":null},{"node":{"durationSeconds":28,"videoOffsetSeconds":264,"viewCount":3},"cursor":null},{"node":{"durationSeconds":26,"videoOffsetSeconds":268,"viewCount":5},"cursor":null},{"node":{"durationSeconds":26,"videoOffsetSeconds":276,"viewCount":1},"cursor":null},{"node":{"durationSeconds":30,"videoOffsetSeconds":288,"viewCount":1},"cursor":null},{"node":{"durationSeconds":26,"videoOffsetSeconds":298,"viewCount":3},"cursor":null},{"node":{"durationSeconds":30,"videoOffsetSeconds":300,"viewCount":1},"cursor":null},{"node":{"durationSeconds":26,"videoOffsetSeconds":306,"viewCount":1},"cursor":null},{"node":{"durationSeconds":28,"videoOffsetSeconds":308,"viewCount":3},"cursor":null},{"node":{"durationSeconds":30,"videoOffsetSeconds":310,"viewCount":1},"cursor":null},{"node":{"durationSeconds":30,"videoOffsetSeconds":320,"viewCount":1},"cursor":null},{"node":{"durationSeconds":30,"videoOffsetSeconds":320,"viewCount":1},"cursor":null},{"node":{"durationSeconds":26,"videoOffsetSeconds":326,"viewCount":1},"cursor":null},{"node":{"durationSeconds":28,"videoOffsetSeconds":352,"viewCount":3},"cursor":null},{"node":{"durationSeconds":26,"videoOffsetSeconds":376,"viewCount":1},"cursor":null},{"node":{"durationSeconds":30,"videoOffsetSeconds":392,"viewCount":1},"cursor":null},{"node":{"durationSeconds":28,"videoOffsetSeconds":398,"viewCount":1},"cursor":null},{"node":{"durationSeconds":26,"videoOffsetSeconds":408,"viewCount":1},"cursor":null},{"node":{"durationSeconds":26,"videoOffsetSeconds":408,"viewCount":1},"cursor":null},{"node":{"durationSeconds":26,"videoOffsetSeconds":408,"viewCount":3},"cursor":null},{"node":{"durationSeconds":30,"videoOffsetSeconds":418,"viewCount":1},"cursor":null},{"node":{"durationSeconds":30,"videoOffsetSeconds":430,"viewCount":1},"cursor":null},{"node":{"durationSeconds":30,"videoOffsetSeconds":430,"viewCount":1},"cursor":null},{"node":{"durationSeconds":30,"videoOffsetSeconds":430,"viewCount":1},"cursor":null},{"node":{"durationSeconds":30,"videoOffsetSeconds":434,"viewCount":1},"cursor":null},{"node":{"durationSeconds":30,"videoOffsetSeconds":436,"viewCount":1},"cursor":null},{"node":{"durationSeconds":30,"videoOffsetSeconds":440,"viewCount":1},"cursor":null},{"node":{"durationSeconds":30,"videoOffsetSeconds":448,"viewCount":1},"cursor":null},{"node":{"durationSeconds":30,"videoOffsetSeconds":454,"viewCount":1},"cursor":null},{"node":{"durationSeconds":26,"videoOffsetSeconds":462,"viewCount":1},"cursor":null},{"node":{"durationSeconds":30,"videoOffsetSeconds":490,"viewCount":1},"cursor":null},{"node":{"durationSeconds":26,"videoOffsetSeconds":504,"viewCount":1},"cursor":null},{"node":{"durationSeconds":26,"videoOffsetSeconds":514,"viewCount":3},"cursor":null},{"node":{"durationSeconds":28,"videoOffsetSeconds":522,"viewCount":1},"cursor":null},{"node":{"durationSeconds":28,"videoOffsetSeconds":550,"viewCount":1},"cursor":null},{"node":{"durationSeconds":26,"videoOffsetSeconds":554,"viewCount":1},"cursor":null},{"node":{"durationSeconds":28,"videoOffsetSeconds":576,"viewCount":3},"cursor":null},{"node":{"durationSeconds":30,"videoOffsetSeconds":588,"viewCount":1},"cursor":null},{"node":{"durationSeconds":30,"videoOffsetSeconds":590,"viewCount":1},"cursor":null},{"node":{"durationSeconds":30,"videoOffsetSeconds":600,"viewCount":1},"cursor":null},{"node":{"durationSeconds":28,"videoOffsetSeconds":628,"viewCount":9},"cursor":null},{"node":{"durationSeconds":26,"videoOffsetSeconds":632,"viewCount":1},"cursor":null},{"node":{"durationSeconds":30,"videoOffsetSeconds":638,"viewCount":1},"cursor":null},{"node":{"durationSeconds":30,"videoOffsetSeconds":642,"viewCount":1},"cursor":null},{"node":{"durationSeconds":26,"videoOffsetSeconds":644,"viewCount":1},"cursor":null},{"node":{"durationSeconds":28,"videoOffsetSeconds":678,"viewCount":1},"cursor":null},{"node":{"durationSeconds":28,"videoOffsetSeconds":692,"viewCount":1},"cursor":null},{"node":{"durationSeconds":28,"videoOffsetSeconds":692,"viewCount":1},"cursor":null},{"node":{"durationSeconds":26,"videoOffsetSeconds":722,"viewCount":1},"cursor":null},{"node":{"durationSeconds":25,"videoOffsetSeconds":725,"viewCount":3},"cursor":null},{"node":{"durationSeconds":28,"videoOffsetSeconds":758,"viewCount":1},"cursor":null},{"node":{"durationSeconds":30,"videoOffsetSeconds":760,"viewCount":1},"cursor":null},{"node":{"durationSeconds":30,"videoOffsetSeconds":770,"viewCount":1},"cursor":null},{"node":{"durationSeconds":28,"videoOffsetSeconds":772,"viewCount":1},"cursor":null},{"node":{"durationSeconds":28,"videoOffsetSeconds":774,"viewCount":3},"cursor":null},{"node":{"durationSeconds":5,"videoOffsetSeconds":782,"viewCount":99},"cursor":null},{"node":{"durationSeconds":26,"videoOffsetSeconds":804,"viewCount":1},"cursor":null},{"node":{"durationSeconds":28,"videoOffsetSeconds":828,"viewCount":1},"cursor":null},{"node":{"durationSeconds":26,"videoOffsetSeconds":850,"viewCount":1},"cursor":"eyJTbHVnIjoiRWxlZ2FudEFtZXJpY2FuTGFtcFJpdHpNaXR6LThlczZ0MFY2YlJPeDN1cmwiLCJWb2RJZCI6IjE1MjM0MjgwNzgiLCJDbGlwTWVkaWFPZmZzZXQiOjg1MH0="},{"node":{"durationSeconds":30,"videoOffsetSeconds":850,"viewCount":1},"cursor":null},{"node":{"durationSeconds":26,"videoOffsetSeconds":850,"viewCount":9},"cursor":null},{"node":{"durationSeconds":26,"videoOffsetSeconds":850,"viewCount":3},"cursor":null},{"node":{"durationSeconds":26,"videoOffsetSeconds":852,"viewCount":3},"cursor":null},{"node":{"durationSeconds":26,"videoOffsetSeconds":852,"viewCount":3},"cursor":null},{"node":{"durationSeconds":26,"videoOffsetSeconds":852,"viewCount":5},"cursor":null},{"node":{"durationSeconds":30,"videoOffsetSeconds":856,"viewCount":3},"cursor":null},{"node":{"durationSeconds":30,"videoOffsetSeconds":860,"viewCount":1},"cursor":null},{"node":{"durationSeconds":28,"videoOffsetSeconds":864,"viewCount":3},"cursor":null},{"node":{"durationSeconds":28,"videoOffsetSeconds":864,"viewCount":3},"cursor":null},{"node":{"durationSeconds":28,"videoOffsetSeconds":870,"viewCount":3},"cursor":null},{"node":{"durationSeconds":30,"videoOffsetSeconds":876,"viewCount":3},"cursor":null},{"node":{"durationSeconds":30,"videoOffsetSeconds":890,"viewCount":1},"cursor":null},{"node":{"durationSeconds":30,"videoOffsetSeconds":912,"viewCount":1},"cursor":null},{"node":{"durationSeconds":30,"videoOffsetSeconds":930,"viewCount":1},"cursor":null},{"node":{"durationSeconds":30,"videoOffsetSeconds":930,"viewCount":7},"cursor":null},{"node":{"durationSeconds":5,"videoOffsetSeconds":934,"viewCount":7},"cursor":null},{"node":{"durationSeconds":26,"videoOffsetSeconds":940,"viewCount":1},"cursor":null},{"node":{"durationSeconds":30,"videoOffsetSeconds":940,"viewCount":1},"cursor":null},{"node":{"durationSeconds":30,"videoOffsetSeconds":956,"viewCount":3},"cursor":null},{"node":{"durationSeconds":30,"videoOffsetSeconds":990,"viewCount":1},"cursor":null},{"node":{"durationSeconds":30,"videoOffsetSeconds":1000,"viewCount":1},"cursor":null},{"node":{"durationSeconds":28,"videoOffsetSeconds":1000,"viewCount":1},"cursor":null},{"node":{"durationSeconds":30,"videoOffsetSeconds":1000,"viewCount":1},"cursor":null},{"node":{"durationSeconds":30,"videoOffsetSeconds":1000,"viewCount":7},"cursor":null},{"node":{"durationSeconds":30,"videoOffsetSeconds":1008,"viewCount":1},"cursor":null},{"node":{"durationSeconds":28,"videoOffsetSeconds":1012,"viewCount":3},"cursor":null},{"node":{"durationSeconds":28,"videoOffsetSeconds":1014,"viewCount":5},"cursor":null},{"node":{"durationSeconds":26,"videoOffsetSeconds":1018,"viewCount":3},"cursor":null},{"node":{"durationSeconds":26,"videoOffsetSeconds":1018,"viewCount":1},"cursor":null},{"node":{"durationSeconds":30,"videoOffsetSeconds":1020,"viewCount":1},"cursor":null},{"node":{"durationSeconds":30,"videoOffsetSeconds":1022,"viewCount":1},"cursor":null},{"node":{"durationSeconds":28,"videoOffsetSeconds":1060,"viewCount":1},"cursor":null},{"node":{"durationSeconds":30,"videoOffsetSeconds":1060,"viewCount":1},"cursor":null},{"node":{"durationSeconds":26,"videoOffsetSeconds":1064,"viewCount":1},"cursor":null},{"node":{"durationSeconds":28,"videoOffsetSeconds":1072,"viewCount":1},"cursor":null},{"node":{"durationSeconds":30,"videoOffsetSeconds":1078,"viewCount":3},"cursor":null},{"node":{"durationSeconds":30,"videoOffsetSeconds":1080,"viewCount":1},"cursor":null},{"node":{"durationSeconds":30,"videoOffsetSeconds":1094,"viewCount":1},"cursor":null},{"node":{"durationSeconds":30,"videoOffsetSeconds":1094,"viewCount":1},"cursor":null},{"node":{"durationSeconds":28,"videoOffsetSeconds":1096,"viewCount":1},"cursor":null},{"node":{"durationSeconds":28,"videoOffsetSeconds":1114,"viewCount":1},"cursor":null},{"node":{"durationSeconds":28,"videoOffsetSeconds":1114,"viewCount":1},"cursor":null},{"node":{"durationSeconds":30,"videoOffsetSeconds":1120,"viewCount":1},"cursor":null},{"node":{"durationSeconds":26,"videoOffsetSeconds":1140,"viewCount":1},"cursor":null},{"node":{"durationSeconds":30,"videoOffsetSeconds":1140,"viewCount":1},"cursor":null},{"node":{"durationSeconds":26,"videoOffsetSeconds":1142,"viewCount":1},"cursor":null},{"node":{"durationSeconds":26,"videoOffsetSeconds":1144,"viewCount":1},"cursor":null},{"node":{"durationSeconds":30,"videoOffsetSeconds":1150,"viewCount":1},"cursor":null},{"node":{"durationSeconds":30,"videoOffsetSeconds":1162,"viewCount":1},"cursor":null},{"node":{"durationSeconds":30,"videoOffsetSeconds":1170,"viewCount":1},"cursor":null},{"node":{"durationSeconds":28,"videoOffsetSeconds":1172,"viewCount":3},"cursor":null},{"node":{"durationSeconds":30,"videoOffsetSeconds":1180,"viewCount":1},"cursor":null},{"node":{"durationSeconds":13,"videoOffsetSeconds":1182,"viewCount":3},"cursor":null},{"node":{"durationSeconds":30,"videoOffsetSeconds":1190,"viewCount":1},"cursor":null},{"node":{"durationSeconds":26,"videoOffsetSeconds":1196,"viewCount":1},"cursor":null},{"node":{"durationSeconds":30,"videoOffsetSeconds":1210,"viewCount":1},"cursor":null},{"node":{"durationSeconds":26,"videoOffsetSeconds":1212,"viewCount":1},"cursor":null},{"node":{"durationSeconds":30,"videoOffsetSeconds":1230,"viewCount":1},"cursor":null},{"node":{"durationSeconds":30,"videoOffsetSeconds":1266,"viewCount":3},"cursor":null},{"node":{"durationSeconds":30,"videoOffsetSeconds":1290,"viewCount":1},"cursor":null},{"node":{"durationSeconds":30,"videoOffsetSeconds":1290,"viewCount":1},"cursor":null},{"node":{"durationSeconds":26,"videoOffsetSeconds":1292,"viewCount":1},"cursor":null},{"node":{"durationSeconds":30,"videoOffsetSeconds":1304,"viewCount":7},"cursor":null},{"node":{"durationSeconds":28,"videoOffsetSeconds":1308,"viewCount":3},"cursor":null},{"node":{"durationSeconds":26,"videoOffsetSeconds":1310,"viewCount":5},"cursor":null},{"node":{"durationSeconds":26,"videoOffsetSeconds":1310,"viewCount":3},"cursor":null},{"node":{"durationSeconds":30,"videoOffsetSeconds":1310,"viewCount":1},"cursor":null},{"node":{"durationSeconds":30,"videoOffsetSeconds":1310,"viewCount":1},"cursor":null},{"node":{"durationSeconds":26,"videoOffsetSeconds":1310,"viewCount":3},"cursor":null},{"node":{"durationSeconds":30,"videoOffsetSeconds":1310,"viewCount":1},"cursor":null},{"node":{"durationSeconds":26,"videoOffsetSeconds":1310,"viewCount":3},"cursor":null},{"node":{"durationSeconds":30,"videoOffsetSeconds":1310,"viewCount":1},"cursor":null},{"node":{"durationSeconds":30,"videoOffsetSeconds":1312,"viewCount":3},"cursor":null},{"node":{"durationSeconds":30,"videoOffsetSeconds":1316,"viewCount":1},"cursor":null},{"node":{"durationSeconds":30,"videoOffsetSeconds":1320,"viewCount":1},"cursor":null},{"node":{"durationSeconds":30,"videoOffsetSeconds":1320,"viewCount":3},"cursor":null},{"node":{"durationSeconds":30,"videoOffsetSeconds":1320,"viewCount":1},"cursor":null},{"node":{"durationSeconds":26,"videoOffsetSeconds":1322,"viewCount":1},"cursor":null},{"node":{"durationSeconds":30,"videoOffsetSeconds":1332,"viewCount":1},"cursor":null},{"node":{"durationSeconds":30,"videoOffsetSeconds":1340,"viewCount":1},"cursor":null},{"node":{"durationSeconds":30,"videoOffsetSeconds":1350,"viewCount":1},"cursor":null},{"node":{"durationSeconds":30,"videoOffsetSeconds":1358,"viewCount":1},"cursor":null},{"node":{"durationSeconds":30,"videoOffsetSeconds":1360,"viewCount":1},"cursor":null},{"node":{"durationSeconds":28,"videoOffsetSeconds":1372,"viewCount":3},"cursor":null},{"node":{"durationSeconds":30,"videoOffsetSeconds":1374,"viewCount":1},"cursor":null},{"node":{"durationSeconds":30,"videoOffsetSeconds":1380,"viewCount":1},"cursor":null},{"node":{"durationSeconds":30,"videoOffsetSeconds":1382,"viewCount":7},"cursor":null},{"node":{"durationSeconds":26,"videoOffsetSeconds":1386,"viewCount":3},"cursor":null},{"node":{"durationSeconds":28,"videoOffsetSeconds":1408,"viewCount":1},"cursor":null},{"node":{"durationSeconds":30,"videoOffsetSeconds":1410,"viewCount":1},"cursor":null},{"node":{"durationSeconds":30,"videoOffsetSeconds":1420,"viewCount":1},"cursor":null},{"node":{"durationSeconds":30,"videoOffsetSeconds":1422,"viewCount":1},"cursor":null},{"node":{"durationSeconds":10,"videoOffsetSeconds":1429,"viewCount":7},"cursor":null},{"node":{"durationSeconds":30,"videoOffsetSeconds":1430,"viewCount":1},"cursor":null},{"node":{"durationSeconds":30,"videoOffsetSeconds":1430,"viewCount":3},"cursor":null},{"node":{"durationSeconds":26,"videoOffsetSeconds":1434,"viewCount":23},"cursor":null},{"node":{"durationSeconds":30,"videoOffsetSeconds":1504,"viewCount":1},"cursor":null},{"node":{"durationSeconds":30,"videoOffsetSeconds":1506,"viewCount":3},"cursor":null},{"node":{"durationSeconds":30,"videoOffsetSeconds":1512,"viewCount":1},"cursor":"eyJTbHVnIjoiSW5zcGlyaW5nQ29uc2lkZXJhdGVNYW5nb0FyZ2llQjgtbWR1ZlJ3NjY5WGpiRGpHRSIsIlZvZElkIjoiMTUyMzQyODA3OCIsIkNsaXBNZWRpYU9mZnNldCI6MTUxMn0="},{"node":{"durationSeconds":26,"videoOffsetSeconds":1520,"viewCount":1},"cursor":null},{"node":{"durationSeconds":26,"videoOffsetSeconds":1530,"viewCount":157},"cursor":null},{"node":{"durationSeconds":28,"videoOffsetSeconds":1536,"viewCount":3},"cursor":null},{"node":{"durationSeconds":28,"videoOffsetSeconds":1538,"viewCount":3},"cursor":null},{"node":{"durationSeconds":30,"videoOffsetSeconds":1580,"viewCount":1},"cursor":null},{"node":{"durationSeconds":30,"videoOffsetSeconds":1582,"viewCount":1},"cursor":null},{"node":{"durationSeconds":30,"videoOffsetSeconds":1596,"viewCount":1},"cursor":null},{"node":{"durationSeconds":28,"videoOffsetSeconds":1600,"viewCount":3},"cursor":null},{"node":{"durationSeconds":30,"videoOffsetSeconds":1610,"viewCount":1},"cursor":null},{"node":{"durationSeconds":30,"videoOffsetSeconds":1620,"viewCount":1},"cursor":null},{"node":{"durationSeconds":30,"videoOffsetSeconds":1622,"viewCount":1},"cursor":null},{"node":{"durationSeconds":28,"videoOffsetSeconds":1628,"viewCount":1},"cursor":null},{"node":{"durationSeconds":30,"videoOffsetSeconds":1630,"viewCount":1},"cursor":null},{"node":{"durationSeconds":31,"videoOffsetSeconds":1640,"viewCount":1},"cursor":null},{"node":{"durationSeconds":31,"videoOffsetSeconds":1640,"viewCount":1},"cursor":null},{"node":{"durationSeconds":31,"videoOffsetSeconds":1640,"viewCount":1},"cursor":null},{"node":{"durationSeconds":23,"videoOffsetSeconds":1648,"viewCount":3},"cursor":null}],"url":{"quality":"Audio Only","resolution":null,"url":"https://d1ymi26ma8va5x.cloudfront.net/730df1c2b7129a06e1de_grenbaud_45710948380_1657059035/audio_only/index-dvr.m3u8"},"len":1672}