{"nc":177,"clips":[{"node":{"durationSeconds":30,"videoOffsetSeconds":576,"viewCount":1},"cursor":null},{"node":{"durationSeconds":26,"videoOffsetSeconds":746,"viewCount":1},"cursor":null},{"node":{"durationSeconds":28,"videoOffsetSeconds":874,"viewCount":1},"cursor":null},{"node":{"durationSeconds":26,"videoOffsetSeconds":976,"viewCount":9},"cursor":null},{"node":{"durationSeconds":28,"videoOffsetSeconds":1098,"viewCount":3},"cursor":null},{"node":{"durationSeconds":30,"videoOffsetSeconds":1270,"viewCount":1},"cursor":null},{"node":{"durationSeconds":60,"videoOffsetSeconds":2004,"viewCount":21},"cursor":null},{"node":{"durationSeconds":55,"videoOffsetSeconds":2005,"viewCount":183},"cursor":null},{"node":{"durationSeconds":26,"videoOffsetSeconds":2010,"viewCount":3},"cursor":null},{"node":{"durationSeconds":59,"videoOffsetSeconds":2017,"viewCount":3},"cursor":null},{"node":{"durationSeconds":53,"videoOffsetSeconds":2019,"viewCount":7},"cursor":null},{"node":{"durationSeconds":28,"videoOffsetSeconds":2052,"viewCount":3},"cursor":null},{"node":{"durationSeconds":54,"videoOffsetSeconds":2059,"viewCount":25},"cursor":null},{"node":{"durationSeconds":28,"videoOffsetSeconds":2076,"viewCount":3},"cursor":null},{"node":{"durationSeconds":30,"videoOffsetSeconds":2178,"viewCount":3},"cursor":null},{"node":{"durationSeconds":30,"videoOffsetSeconds":2676,"viewCount":3},"cursor":null},{"node":{"durationSeconds":28,"videoOffsetSeconds":2830,"viewCount":1},"cursor":null},{"node":{"durationSeconds":30,"videoOffsetSeconds":2970,"viewCount":3},"cursor":null},{"node":{"durationSeconds":30,"videoOffsetSeconds":2994,"viewCount":1},"cursor":null},{"node":{"durationSeconds":30,"videoOffsetSeconds":3084,"viewCount":1},"cursor":null},{"node":{"durationSeconds":28,"videoOffsetSeconds":3220,"viewCount":1},"cursor":null},{"node":{"durationSeconds":28,"videoOffsetSeconds":3612,"viewCount":1},"cursor":null},{"node":{"durationSeconds":30,"videoOffsetSeconds":3660,"viewCount":1},"cursor":null},{"node":{"durationSeconds":30,"videoOffsetSeconds":3680,"viewCount":5},"cursor":null},{"node":{"durationSeconds":30,"videoOffsetSeconds":3762,"viewCount":3},"cursor":null},{"node":{"durationSeconds":28,"videoOffsetSeconds":3788,"viewCount":1},"cursor":null},{"node":{"durationSeconds":30,"videoOffsetSeconds":3854,"viewCount":3},"cursor":null},{"node":{"durationSeconds":28,"videoOffsetSeconds":4290,"viewCount":9},"cursor":null},{"node":{"durationSeconds":30,"videoOffsetSeconds":4344,"viewCount":1},"cursor":null},{"node":{"durationSeconds":30,"videoOffsetSeconds":4960,"viewCount":5},"cursor":null},{"node":{"durationSeconds":26,"videoOffsetSeconds":5100,"viewCount":1},"cursor":null},{"node":{"durationSeconds":30,"videoOffsetSeconds":5396,"viewCount":3},"cursor":null},{"node":{"durationSeconds":30,"videoOffsetSeconds":5836,"viewCount":1},"cursor":null},{"node":{"durationSeconds":59,"videoOffsetSeconds":5886,"viewCount":55},"cursor":null},{"node":{"durationSeconds":30,"videoOffsetSeconds":5910,"viewCount":1},"cursor":null},{"node":{"durationSeconds":36,"videoOffsetSeconds":6087,"viewCount":43},"cursor":null},{"node":{"durationSeconds":28,"videoOffsetSeconds":6096,"viewCount":15},"cursor":null},{"node":{"durationSeconds":30,"videoOffsetSeconds":6112,"viewCount":3},"cursor":null},{"node":{"durationSeconds":48,"videoOffsetSeconds":6248,"viewCount":39},"cursor":null},{"node":{"durationSeconds":28,"videoOffsetSeconds":6786,"viewCount":1},"cursor":null},{"node":{"durationSeconds":30,"videoOffsetSeconds":7294,"viewCount":108},"cursor":null},{"node":{"durationSeconds":52,"videoOffsetSeconds":7301,"viewCount":33},"cursor":null},{"node":{"durationSeconds":59,"videoOffsetSeconds":7304,"viewCount":35},"cursor":null},{"node":{"durationSeconds":26,"videoOffsetSeconds":7330,"viewCount":3},"cursor":null},{"node":{"durationSeconds":28,"videoOffsetSeconds":7676,"viewCount":1},"cursor":null},{"node":{"durationSeconds":26,"videoOffsetSeconds":7838,"viewCount":1},"cursor":null},{"node":{"durationSeconds":60,"videoOffsetSeconds":7920,"viewCount":65},"cursor":null},{"node":{"durationSeconds":28,"videoOffsetSeconds":7942,"viewCount":3},"cursor":null},{"node":{"durationSeconds":30,"videoOffsetSeconds":7950,"viewCount":1},"cursor":null},{"node":{"durationSeconds":30,"videoOffsetSeconds":8022,"viewCount":3},"cursor":null},{"node":{"durationSeconds":26,"videoOffsetSeconds":8362,"viewCount":3},"cursor":null},{"node":{"durationSeconds":30,"videoOffsetSeconds":8418,"viewCount":1},"cursor":null},{"node":{"durationSeconds":59,"videoOffsetSeconds":8466,"viewCount":43},"cursor":null},{"node":{"durationSeconds":30,"videoOffsetSeconds":8486,"viewCount":1},"cursor":null},{"node":{"durationSeconds":30,"videoOffsetSeconds":8490,"viewCount":1},"cursor":null},{"node":{"durationSeconds":30,"videoOffsetSeconds":8498,"viewCount":3},"cursor":null},{"node":{"durationSeconds":28,"videoOffsetSeconds":8520,"viewCount":3},"cursor":null},{"node":{"durationSeconds":30,"videoOffsetSeconds":8764,"viewCount":3},"cursor":null},{"node":{"durationSeconds":30,"videoOffsetSeconds":9290,"viewCount":1},"cursor":null},{"node":{"durationSeconds":30,"videoOffsetSeconds":11172,"viewCount":3},"cursor":null},{"node":{"durationSeconds":30,"videoOffsetSeconds":11310,"viewCount":1},"cursor":null},{"node":{"durationSeconds":30,"videoOffsetSeconds":11378,"viewCount":1},"cursor":null},{"node":{"durationSeconds":30,"videoOffsetSeconds":12280,"viewCount":1},"cursor":null},{"node":{"durationSeconds":30,"videoOffsetSeconds":12506,"viewCount":1},"cursor":null},{"node":{"durationSeconds":30,"videoOffsetSeconds":12780,"viewCount":1},"cursor":null},{"node":{"durationSeconds":30,"videoOffsetSeconds":12880,"viewCount":1},"cursor":null},{"node":{"durationSeconds":30,"videoOffsetSeconds":13000,"viewCount":1},"cursor":null},{"node":{"durationSeconds":59,"videoOffsetSeconds":13074,"viewCount":41},"cursor":null},{"node":{"durationSeconds":28,"videoOffsetSeconds":13232,"viewCount":97},"cursor":null},{"node":{"durationSeconds":28,"videoOffsetSeconds":13264,"viewCount":3},"cursor":null},{"node":{"durationSeconds":30,"videoOffsetSeconds":13266,"viewCount":3},"cursor":null},{"node":{"durationSeconds":26,"videoOffsetSeconds":13372,"viewCount":3},"cursor":null},{"node":{"durationSeconds":30,"videoOffsetSeconds":13440,"viewCount":5},"cursor":null},{"node":{"durationSeconds":30,"videoOffsetSeconds":13450,"viewCount":1},"cursor":null},{"node":{"durationSeconds":28,"videoOffsetSeconds":13456,"viewCount":1},"cursor":null},{"node":{"durationSeconds":30,"videoOffsetSeconds":13530,"viewCount":3},"cursor":null},{"node":{"durationSeconds":50,"videoOffsetSeconds":13533,"viewCount":3},"cursor":null},{"node":{"durationSeconds":26,"videoOffsetSeconds":13552,"viewCount":215},"cursor":null},{"node":{"durationSeconds":30,"videoOffsetSeconds":13558,"viewCount":1},"cursor":null},{"node":{"durationSeconds":26,"videoOffsetSeconds":13602,"viewCount":5},"cursor":null},{"node":{"durationSeconds":26,"videoOffsetSeconds":13602,"viewCount":1},"cursor":null},{"node":{"durationSeconds":28,"videoOffsetSeconds":13608,"viewCount":21},"cursor":null},{"node":{"durationSeconds":30,"videoOffsetSeconds":13614,"viewCount":3},"cursor":null},{"node":{"durationSeconds":28,"videoOffsetSeconds":13648,"viewCount":3},"cursor":null},{"node":{"durationSeconds":30,"videoOffsetSeconds":13656,"viewCount":3},"cursor":null},{"node":{"durationSeconds":28,"videoOffsetSeconds":13734,"viewCount":1},"cursor":null},{"node":{"durationSeconds":30,"videoOffsetSeconds":13790,"viewCount":1},"cursor":null},{"node":{"durationSeconds":30,"videoOffsetSeconds":13790,"viewCount":1},"cursor":null},{"node":{"durationSeconds":26,"videoOffsetSeconds":13794,"viewCount":3},"cursor":null},{"node":{"durationSeconds":26,"videoOffsetSeconds":13794,"viewCount":3},"cursor":null},{"node":{"durationSeconds":26,"videoOffsetSeconds":13800,"viewCount":11},"cursor":null},{"node":{"durationSeconds":26,"videoOffsetSeconds":13802,"viewCount":3},"cursor":null},{"node":{"durationSeconds":30,"videoOffsetSeconds":13806,"viewCount":3},"cursor":null},{"node":{"durationSeconds":30,"videoOffsetSeconds":13806,"viewCount":7},"cursor":null},{"node":{"durationSeconds":30,"videoOffsetSeconds":13826,"viewCount":1},"cursor":null},{"node":{"durationSeconds":17,"videoOffsetSeconds":13938,"viewCount":9},"cursor":null},{"node":{"durationSeconds":26,"videoOffsetSeconds":13994,"viewCount":1},"cursor":null},{"node":{"durationSeconds":51,"videoOffsetSeconds":14100,"viewCount":41},"cursor":null},{"node":{"durationSeconds":30,"videoOffsetSeconds":14103,"viewCount":3},"cursor":null},{"node":{"durationSeconds":26,"videoOffsetSeconds":14108,"viewCount":1},"cursor":"eyJTbHVnIjoiSGlsYXJpb3VzTWlzdHlKYWxhcGVub1lvdVdIWS1pbUpNOUwxX2lSYU5Fck9xIiwiVm9kSWQiOiIxNTI1MTAwODQzIiwiQ2xpcE1lZGlhT2Zmc2V0IjoxNDEwOH0="},{"node":{"durationSeconds":26,"videoOffsetSeconds":14110,"viewCount":9},"cursor":null},{"node":{"durationSeconds":30,"videoOffsetSeconds":14110,"viewCount":3},"cursor":null},{"node":{"durationSeconds":30,"videoOffsetSeconds":14120,"viewCount":3},"cursor":null},{"node":{"durationSeconds":36,"videoOffsetSeconds":14163,"viewCount":15},"cursor":null},{"node":{"durationSeconds":30,"videoOffsetSeconds":14170,"viewCount":3},"cursor":null},{"node":{"durationSeconds":12,"videoOffsetSeconds":14175,"viewCount":90},"cursor":null},{"node":{"durationSeconds":38,"videoOffsetSeconds":14301,"viewCount":837},"cursor":null},{"node":{"durationSeconds":44,"videoOffsetSeconds":14302,"viewCount":3},"cursor":null},{"node":{"durationSeconds":28,"videoOffsetSeconds":14304,"viewCount":1},"cursor":null},{"node":{"durationSeconds":28,"videoOffsetSeconds":14304,"viewCount":1},"cursor":null},{"node":{"durationSeconds":35,"videoOffsetSeconds":14306,"viewCount":3},"cursor":null},{"node":{"durationSeconds":30,"videoOffsetSeconds":14310,"viewCount":3},"cursor":null},{"node":{"durationSeconds":28,"videoOffsetSeconds":14316,"viewCount":3},"cursor":null},{"node":{"durationSeconds":28,"videoOffsetSeconds":14316,"viewCount":3},"cursor":null},{"node":{"durationSeconds":30,"videoOffsetSeconds":14320,"viewCount":1},"cursor":null},{"node":{"durationSeconds":60,"videoOffsetSeconds":14320,"viewCount":43},"cursor":null},{"node":{"durationSeconds":30,"videoOffsetSeconds":14322,"viewCount":3},"cursor":null},{"node":{"durationSeconds":30,"videoOffsetSeconds":14326,"viewCount":1},"cursor":null},{"node":{"durationSeconds":30,"videoOffsetSeconds":14330,"viewCount":1},"cursor":null},{"node":{"durationSeconds":30,"videoOffsetSeconds":14424,"viewCount":3},"cursor":null},{"node":{"durationSeconds":26,"videoOffsetSeconds":14626,"viewCount":1},"cursor":null},{"node":{"durationSeconds":30,"videoOffsetSeconds":14650,"viewCount":27},"cursor":null},{"node":{"durationSeconds":30,"videoOffsetSeconds":14680,"viewCount":5},"cursor":null},{"node":{"durationSeconds":30,"videoOffsetSeconds":14694,"viewCount":3},"cursor":null},{"node":{"durationSeconds":30,"videoOffsetSeconds":14700,"viewCount":3},"cursor":null},{"node":{"durationSeconds":59,"videoOffsetSeconds":14728,"viewCount":119},"cursor":null},{"node":{"durationSeconds":30,"videoOffsetSeconds":14750,"viewCount":1},"cursor":null},{"node":{"durationSeconds":30,"videoOffsetSeconds":14780,"viewCount":3},"cursor":null},{"node":{"durationSeconds":26,"videoOffsetSeconds":14780,"viewCount":3},"cursor":null},{"node":{"durationSeconds":30,"videoOffsetSeconds":14854,"viewCount":1},"cursor":null},{"node":{"durationSeconds":30,"videoOffsetSeconds":15030,"viewCount":1},"cursor":null},{"node":{"durationSeconds":53,"videoOffsetSeconds":15038,"viewCount":33},"cursor":null},{"node":{"durationSeconds":30,"videoOffsetSeconds":15050,"viewCount":1},"cursor":null},{"node":{"durationSeconds":30,"videoOffsetSeconds":15080,"viewCount":3},"cursor":null},{"node":{"durationSeconds":54,"videoOffsetSeconds":15201,"viewCount":3},"cursor":null},{"node":{"durationSeconds":60,"videoOffsetSeconds":15224,"viewCount":3},"cursor":null},{"node":{"durationSeconds":54,"videoOffsetSeconds":15224,"viewCount":137},"cursor":null},{"node":{"durationSeconds":26,"videoOffsetSeconds":15336,"viewCount":1},"cursor":null},{"node":{"durationSeconds":30,"videoOffsetSeconds":15360,"viewCount":1},"cursor":null},{"node":{"durationSeconds":30,"videoOffsetSeconds":15370,"viewCount":1},"cursor":null},{"node":{"durationSeconds":30,"videoOffsetSeconds":15372,"viewCount":3},"cursor":null},{"node":{"durationSeconds":30,"videoOffsetSeconds":15390,"viewCount":3},"cursor":null},{"node":{"durationSeconds":60,"videoOffsetSeconds":15700,"viewCount":41},"cursor":null},{"node":{"durationSeconds":28,"videoOffsetSeconds":15812,"viewCount":1},"cursor":null},{"node":{"durationSeconds":26,"videoOffsetSeconds":16222,"viewCount":3},"cursor":null},{"node":{"durationSeconds":26,"videoOffsetSeconds":16648,"viewCount":1},"cursor":null},{"node":{"durationSeconds":26,"videoOffsetSeconds":16672,"viewCount":1},"cursor":null},{"node":{"durationSeconds":28,"videoOffsetSeconds":16830,"viewCount":1},"cursor":null},{"node":{"durationSeconds":30,"videoOffsetSeconds":16864,"viewCount":1},"cursor":null},{"node":{"durationSeconds":30,"videoOffsetSeconds":17042,"viewCount":1},"cursor":null},{"node":{"durationSeconds":30,"videoOffsetSeconds":17048,"viewCount":1},"cursor":null},{"node":{"durationSeconds":28,"videoOffsetSeconds":17084,"viewCount":1},"cursor":null},{"node":{"durationSeconds":26,"videoOffsetSeconds":17100,"viewCount":1},"cursor":null},{"node":{"durationSeconds":28,"videoOffsetSeconds":17114,"viewCount":1},"cursor":null},{"node":{"durationSeconds":30,"videoOffsetSeconds":17182,"viewCount":3},"cursor":null},{"node":{"durationSeconds":30,"videoOffsetSeconds":17200,"viewCount":3},"cursor":null},{"node":{"durationSeconds":28,"videoOffsetSeconds":17214,"viewCount":3},"cursor":null},{"node":{"durationSeconds":30,"videoOffsetSeconds":17252,"viewCount":1},"cursor":null},{"node":{"durationSeconds":28,"videoOffsetSeconds":17262,"viewCount":1},"cursor":null},{"node":{"durationSeconds":30,"videoOffsetSeconds":17530,"viewCount":3},"cursor":null},{"node":{"durationSeconds":30,"videoOffsetSeconds":17600,"viewCount":1},"cursor":null},{"node":{"durationSeconds":26,"videoOffsetSeconds":17836,"viewCount":1},"cursor":null},{"node":{"durationSeconds":26,"videoOffsetSeconds":18014,"viewCount":1},"cursor":null},{"node":{"durationSeconds":57,"videoOffsetSeconds":18148,"viewCount":3},"cursor":null},{"node":{"durationSeconds":28,"videoOffsetSeconds":18172,"viewCount":1},"cursor":null},{"node":{"durationSeconds":26,"videoOffsetSeconds":18194,"viewCount":1},"cursor":null},{"node":{"durationSeconds":26,"videoOffsetSeconds":18292,"viewCount":1},"cursor":null},{"node":{"durationSeconds":30,"videoOffsetSeconds":18334,"viewCount":3},"cursor":null},{"node":{"durationSeconds":30,"videoOffsetSeconds":18356,"viewCount":3},"cursor":null},{"node":{"durationSeconds":26,"videoOffsetSeconds":18390,"viewCount":5},"cursor":null},{"node":{"durationSeconds":30,"videoOffsetSeconds":18410,"viewCount":3},"cursor":null},{"node":{"durationSeconds":28,"videoOffsetSeconds":18434,"viewCount":1},"cursor":null},{"node":{"durationSeconds":30,"videoOffsetSeconds":18494,"viewCount":3},"cursor":null},{"node":{"durationSeconds":28,"videoOffsetSeconds":18498,"viewCount":3},"cursor":null},{"node":{"durationSeconds":30,"videoOffsetSeconds":18582,"viewCount":3},"cursor":null},{"node":{"durationSeconds":28,"videoOffsetSeconds":18584,"viewCount":3},"cursor":null},{"node":{"durationSeconds":28,"videoOffsetSeconds":18648,"viewCount":1},"cursor":null}],"url":{"quality":"Audio Only","resolution":null,"url":"https://d1ymi26ma8va5x.cloudfront.net/2abcc15f63256daccc5e_littlebigwhale_45720011724_1657215494/audio_only/index-dvr.m3u8"},"len":19070}