{"nc":108,"clips":[{"node":{"durationSeconds":28,"videoOffsetSeconds":1010,"viewCount":1},"cursor":null},{"node":{"durationSeconds":30,"videoOffsetSeconds":1640,"viewCount":1},"cursor":null},{"node":{"durationSeconds":25,"videoOffsetSeconds":1809,"viewCount":1},"cursor":null},{"node":{"durationSeconds":30,"videoOffsetSeconds":2172,"viewCount":1},"cursor":null},{"node":{"durationSeconds":26,"videoOffsetSeconds":2804,"viewCount":51},"cursor":null},{"node":{"durationSeconds":16,"videoOffsetSeconds":3568,"viewCount":1},"cursor":null},{"node":{"durationSeconds":30,"videoOffsetSeconds":5232,"viewCount":1},"cursor":null},{"node":{"durationSeconds":30,"videoOffsetSeconds":5548,"viewCount":1},"cursor":null},{"node":{"durationSeconds":30,"videoOffsetSeconds":6405,"viewCount":1},"cursor":null},{"node":{"durationSeconds":30,"videoOffsetSeconds":6803,"viewCount":1},"cursor":null},{"node":{"durationSeconds":30,"videoOffsetSeconds":7354,"viewCount":1},"cursor":null},{"node":{"durationSeconds":27,"videoOffsetSeconds":7838,"viewCount":7},"cursor":null},{"node":{"durationSeconds":30,"videoOffsetSeconds":7843,"viewCount":5},"cursor":null},{"node":{"durationSeconds":30,"videoOffsetSeconds":8016,"viewCount":21},"cursor":null},{"node":{"durationSeconds":30,"videoOffsetSeconds":8115,"viewCount":1},"cursor":null},{"node":{"durationSeconds":30,"videoOffsetSeconds":8545,"viewCount":3},"cursor":null},{"node":{"durationSeconds":29,"videoOffsetSeconds":9053,"viewCount":3},"cursor":null},{"node":{"durationSeconds":30,"videoOffsetSeconds":9130,"viewCount":1},"cursor":null},{"node":{"durationSeconds":28,"videoOffsetSeconds":9380,"viewCount":1},"cursor":null},{"node":{"durationSeconds":30,"videoOffsetSeconds":9386,"viewCount":1},"cursor":null},{"node":{"durationSeconds":28,"videoOffsetSeconds":9394,"viewCount":5},"cursor":null},{"node":{"durationSeconds":30,"videoOffsetSeconds":9396,"viewCount":25},"cursor":null},{"node":{"durationSeconds":28,"videoOffsetSeconds":9402,"viewCount":17},"cursor":null},{"node":{"durationSeconds":28,"videoOffsetSeconds":9408,"viewCount":5},"cursor":null},{"node":{"durationSeconds":30,"videoOffsetSeconds":9418,"viewCount":3},"cursor":null},{"node":{"durationSeconds":28,"videoOffsetSeconds":10010,"viewCount":3},"cursor":null},{"node":{"durationSeconds":30,"videoOffsetSeconds":10014,"viewCount":17},"cursor":null},{"node":{"durationSeconds":28,"videoOffsetSeconds":10021,"viewCount":3},"cursor":null},{"node":{"durationSeconds":30,"videoOffsetSeconds":10035,"viewCount":1},"cursor":null},{"node":{"durationSeconds":30,"videoOffsetSeconds":10217,"viewCount":1},"cursor":null},{"node":{"durationSeconds":26,"videoOffsetSeconds":10295,"viewCount":1},"cursor":null},{"node":{"durationSeconds":28,"videoOffsetSeconds":10311,"viewCount":1},"cursor":null},{"node":{"durationSeconds":30,"videoOffsetSeconds":10437,"viewCount":1},"cursor":null},{"node":{"durationSeconds":30,"videoOffsetSeconds":10437,"viewCount":1},"cursor":null},{"node":{"durationSeconds":28,"videoOffsetSeconds":10637,"viewCount":1},"cursor":null},{"node":{"durationSeconds":30,"videoOffsetSeconds":10807,"viewCount":1},"cursor":null},{"node":{"durationSeconds":30,"videoOffsetSeconds":10965,"viewCount":3},"cursor":null},{"node":{"durationSeconds":30,"videoOffsetSeconds":10983,"viewCount":1},"cursor":null},{"node":{"durationSeconds":30,"videoOffsetSeconds":11021,"viewCount":3},"cursor":null},{"node":{"durationSeconds":30,"videoOffsetSeconds":11613,"viewCount":1},"cursor":null},{"node":{"durationSeconds":28,"videoOffsetSeconds":11627,"viewCount":1},"cursor":null},{"node":{"durationSeconds":28,"videoOffsetSeconds":13123,"viewCount":7},"cursor":null},{"node":{"durationSeconds":30,"videoOffsetSeconds":13125,"viewCount":3},"cursor":null},{"node":{"durationSeconds":51,"videoOffsetSeconds":13184,"viewCount":7},"cursor":null},{"node":{"durationSeconds":30,"videoOffsetSeconds":14226,"viewCount":5},"cursor":null},{"node":{"durationSeconds":30,"videoOffsetSeconds":14230,"viewCount":13},"cursor":null},{"node":{"durationSeconds":21,"videoOffsetSeconds":14245,"viewCount":23},"cursor":null},{"node":{"durationSeconds":30,"videoOffsetSeconds":15144,"viewCount":21},"cursor":null},{"node":{"durationSeconds":30,"videoOffsetSeconds":15272,"viewCount":5},"cursor":null},{"node":{"durationSeconds":28,"videoOffsetSeconds":15548,"viewCount":1},"cursor":null},{"node":{"durationSeconds":28,"videoOffsetSeconds":15616,"viewCount":3},"cursor":null},{"node":{"durationSeconds":28,"videoOffsetSeconds":15616,"viewCount":15},"cursor":null},{"node":{"durationSeconds":30,"videoOffsetSeconds":15744,"viewCount":1},"cursor":null},{"node":{"durationSeconds":26,"videoOffsetSeconds":15856,"viewCount":1},"cursor":null},{"node":{"durationSeconds":28,"videoOffsetSeconds":15924,"viewCount":1},"cursor":null},{"node":{"durationSeconds":30,"videoOffsetSeconds":16412,"viewCount":1},"cursor":null},{"node":{"durationSeconds":30,"videoOffsetSeconds":16418,"viewCount":5},"cursor":null},{"node":{"durationSeconds":50,"videoOffsetSeconds":16558,"viewCount":1},"cursor":null},{"node":{"durationSeconds":28,"videoOffsetSeconds":16570,"viewCount":3},"cursor":null},{"node":{"durationSeconds":26,"videoOffsetSeconds":16584,"viewCount":1},"cursor":null},{"node":{"durationSeconds":26,"videoOffsetSeconds":16588,"viewCount":1},"cursor":null},{"node":{"durationSeconds":28,"videoOffsetSeconds":16610,"viewCount":3},"cursor":null},{"node":{"durationSeconds":28,"videoOffsetSeconds":16644,"viewCount":1},"cursor":null},{"node":{"durationSeconds":26,"videoOffsetSeconds":16676,"viewCount":3},"cursor":null},{"node":{"durationSeconds":30,"videoOffsetSeconds":17879,"viewCount":1},"cursor":null},{"node":{"durationSeconds":29,"videoOffsetSeconds":18421,"viewCount":5},"cursor":null},{"node":{"durationSeconds":30,"videoOffsetSeconds":18874,"viewCount":1},"cursor":null},{"node":{"durationSeconds":30,"videoOffsetSeconds":19343,"viewCount":1},"cursor":null},{"node":{"durationSeconds":28,"videoOffsetSeconds":19365,"viewCount":1},"cursor":null},{"node":{"durationSeconds":26,"videoOffsetSeconds":20013,"viewCount":3},"cursor":null},{"node":{"durationSeconds":26,"videoOffsetSeconds":20081,"viewCount":5},"cursor":null},{"node":{"durationSeconds":30,"videoOffsetSeconds":20667,"viewCount":1},"cursor":null},{"node":{"durationSeconds":30,"videoOffsetSeconds":20671,"viewCount":1},"cursor":null},{"node":{"durationSeconds":26,"videoOffsetSeconds":20880,"viewCount":3},"cursor":null},{"node":{"durationSeconds":26,"videoOffsetSeconds":20880,"viewCount":1},"cursor":null},{"node":{"durationSeconds":30,"videoOffsetSeconds":20882,"viewCount":3},"cursor":null},{"node":{"durationSeconds":29,"videoOffsetSeconds":20888,"viewCount":3},"cursor":null},{"node":{"durationSeconds":30,"videoOffsetSeconds":21066,"viewCount":11},"cursor":null},{"node":{"durationSeconds":30,"videoOffsetSeconds":21196,"viewCount":5},"cursor":null},{"node":{"durationSeconds":29,"videoOffsetSeconds":21246,"viewCount":11},"cursor":null},{"node":{"durationSeconds":59,"videoOffsetSeconds":21320,"viewCount":11},"cursor":null},{"node":{"durationSeconds":28,"videoOffsetSeconds":21579,"viewCount":1},"cursor":null},{"node":{"durationSeconds":30,"videoOffsetSeconds":21729,"viewCount":3},"cursor":null},{"node":{"durationSeconds":30,"videoOffsetSeconds":21781,"viewCount":3},"cursor":null},{"node":{"durationSeconds":50,"videoOffsetSeconds":21823,"viewCount":1},"cursor":null},{"node":{"durationSeconds":38,"videoOffsetSeconds":21826,"viewCount":3},"cursor":null},{"node":{"durationSeconds":30,"videoOffsetSeconds":21833,"viewCount":1},"cursor":null},{"node":{"durationSeconds":30,"videoOffsetSeconds":21877,"viewCount":3},"cursor":null},{"node":{"durationSeconds":28,"videoOffsetSeconds":21891,"viewCount":1},"cursor":null},{"node":{"durationSeconds":26,"videoOffsetSeconds":21913,"viewCount":3},"cursor":null},{"node":{"durationSeconds":30,"videoOffsetSeconds":22083,"viewCount":3},"cursor":null},{"node":{"durationSeconds":29,"videoOffsetSeconds":22354,"viewCount":1},"cursor":null},{"node":{"durationSeconds":30,"videoOffsetSeconds":22444,"viewCount":5},"cursor":null},{"node":{"durationSeconds":27,"videoOffsetSeconds":22500,"viewCount":63},"cursor":null},{"node":{"durationSeconds":60,"videoOffsetSeconds":23150,"viewCount":15},"cursor":null},{"node":{"durationSeconds":30,"videoOffsetSeconds":23250,"viewCount":1},"cursor":null},{"node":{"durationSeconds":30,"videoOffsetSeconds":23420,"viewCount":1},"cursor":null},{"node":{"durationSeconds":26,"videoOffsetSeconds":23699,"viewCount":3},"cursor":null},{"node":{"durationSeconds":30,"videoOffsetSeconds":23916,"viewCount":3},"cursor":null},{"node":{"durationSeconds":30,"videoOffsetSeconds":23926,"viewCount":5},"cursor":"eyJTbHVnIjoiQmxvb2R5RnJpZW5kbHlTbW9vdGhpZUFsaWVucy1EMTBBV2M5T0ptRks2a05CIiwiVm9kSWQiOiIxNTIzNTMzNjc5IiwiQ2xpcE1lZGlhT2Zmc2V0IjoyMzkyNi45NX0="},{"node":{"durationSeconds":59,"videoOffsetSeconds":24427,"viewCount":1},"cursor":null},{"node":{"durationSeconds":30,"videoOffsetSeconds":24473,"viewCount":13},"cursor":null},{"node":{"durationSeconds":30,"videoOffsetSeconds":24603,"viewCount":3},"cursor":null},{"node":{"durationSeconds":28,"videoOffsetSeconds":24954,"viewCount":3},"cursor":null},{"node":{"durationSeconds":28,"videoOffsetSeconds":26101,"viewCount":1},"cursor":null},{"node":{"durationSeconds":28,"videoOffsetSeconds":28373,"viewCount":3},"cursor":null},{"node":{"durationSeconds":26,"videoOffsetSeconds":28407,"viewCount":3},"cursor":null},{"node":{"durationSeconds":30,"videoOffsetSeconds":28417,"viewCount":7},"cursor":null}],"url":{"quality":"Audio Only","resolution":null,"url":"https://d2vjef5jvl6bfs.cloudfront.net/180a7aef5dc4e8844dfc_delt4forc3_46744519805_1657066372/audio_only/index-dvr.m3u8"},"len":28846}