{"nc":7,"clips":[{"node":{"durationSeconds":29,"videoOffsetSeconds":3360,"viewCount":183},"cursor":null},{"node":{"durationSeconds":29,"videoOffsetSeconds":4475,"viewCount":97},"cursor":null},{"node":{"durationSeconds":28,"videoOffsetSeconds":20216,"viewCount":93},"cursor":null},{"node":{"durationSeconds":29,"videoOffsetSeconds":21735,"viewCount":43},"cursor":null},{"node":{"durationSeconds":28,"videoOffsetSeconds":22178,"viewCount":39},"cursor":null},{"node":{"durationSeconds":26,"videoOffsetSeconds":23781,"viewCount":53},"cursor":null},{"node":{"durationSeconds":29,"videoOffsetSeconds":24021,"viewCount":53},"cursor":null}],"url":{"quality":"Audio Only","resolution":null,"url":"https://d1mhjrowxxagfy.cloudfront.net/33afeab931ae3fbb1961_bunniejin_39470451239_1657261765/audio_only/index-muted-NXS32E65F6.m3u8"},"len":25531}