{"nc":446,"clips":[{"node":{"durationSeconds":10,"videoOffsetSeconds":0,"viewCount":1},"cursor":null},{"node":{"durationSeconds":30,"videoOffsetSeconds":40,"viewCount":1},"cursor":null},{"node":{"durationSeconds":30,"videoOffsetSeconds":120,"viewCount":1},"cursor":null},{"node":{"durationSeconds":30,"videoOffsetSeconds":130,"viewCount":1},"cursor":null},{"node":{"durationSeconds":26,"videoOffsetSeconds":144,"viewCount":7},"cursor":null},{"node":{"durationSeconds":30,"videoOffsetSeconds":170,"viewCount":1},"cursor":null},{"node":{"durationSeconds":26,"videoOffsetSeconds":202,"viewCount":1},"cursor":null},{"node":{"durationSeconds":30,"videoOffsetSeconds":248,"viewCount":1},"cursor":null},{"node":{"durationSeconds":30,"videoOffsetSeconds":266,"viewCount":1},"cursor":null},{"node":{"durationSeconds":30,"videoOffsetSeconds":280,"viewCount":3},"cursor":null},{"node":{"durationSeconds":26,"videoOffsetSeconds":290,"viewCount":1},"cursor":null},{"node":{"durationSeconds":30,"videoOffsetSeconds":406,"viewCount":1},"cursor":null},{"node":{"durationSeconds":30,"videoOffsetSeconds":426,"viewCount":1},"cursor":null},{"node":{"durationSeconds":30,"videoOffsetSeconds":486,"viewCount":1},"cursor":null},{"node":{"durationSeconds":28,"videoOffsetSeconds":508,"viewCount":1},"cursor":null},{"node":{"durationSeconds":30,"videoOffsetSeconds":572,"viewCount":1},"cursor":null},{"node":{"durationSeconds":30,"videoOffsetSeconds":618,"viewCount":1},"cursor":null},{"node":{"durationSeconds":30,"videoOffsetSeconds":674,"viewCount":1},"cursor":null},{"node":{"durationSeconds":30,"videoOffsetSeconds":700,"viewCount":1},"cursor":null},{"node":{"durationSeconds":30,"videoOffsetSeconds":708,"viewCount":1},"cursor":null},{"node":{"durationSeconds":30,"videoOffsetSeconds":760,"viewCount":1},"cursor":null},{"node":{"durationSeconds":26,"videoOffsetSeconds":762,"viewCount":1},"cursor":null},{"node":{"durationSeconds":30,"videoOffsetSeconds":830,"viewCount":1},"cursor":null},{"node":{"durationSeconds":30,"videoOffsetSeconds":840,"viewCount":1},"cursor":null},{"node":{"durationSeconds":26,"videoOffsetSeconds":906,"viewCount":11},"cursor":null},{"node":{"durationSeconds":26,"videoOffsetSeconds":906,"viewCount":1},"cursor":null},{"node":{"durationSeconds":6,"videoOffsetSeconds":944,"viewCount":5},"cursor":null},{"node":{"durationSeconds":28,"videoOffsetSeconds":950,"viewCount":1},"cursor":null},{"node":{"durationSeconds":30,"videoOffsetSeconds":1060,"viewCount":1},"cursor":null},{"node":{"durationSeconds":30,"videoOffsetSeconds":1082,"viewCount":3},"cursor":null},{"node":{"durationSeconds":30,"videoOffsetSeconds":1098,"viewCount":3},"cursor":null},{"node":{"durationSeconds":30,"videoOffsetSeconds":1170,"viewCount":1},"cursor":null},{"node":{"durationSeconds":30,"videoOffsetSeconds":1206,"viewCount":1},"cursor":null},{"node":{"durationSeconds":30,"videoOffsetSeconds":1228,"viewCount":3},"cursor":null},{"node":{"durationSeconds":28,"videoOffsetSeconds":1248,"viewCount":1},"cursor":null},{"node":{"durationSeconds":30,"videoOffsetSeconds":1286,"viewCount":1},"cursor":null},{"node":{"durationSeconds":30,"videoOffsetSeconds":1300,"viewCount":1},"cursor":null},{"node":{"durationSeconds":30,"videoOffsetSeconds":1308,"viewCount":1},"cursor":null},{"node":{"durationSeconds":26,"videoOffsetSeconds":1404,"viewCount":1},"cursor":null},{"node":{"durationSeconds":26,"videoOffsetSeconds":1438,"viewCount":1},"cursor":null},{"node":{"durationSeconds":30,"videoOffsetSeconds":1462,"viewCount":1},"cursor":null},{"node":{"durationSeconds":26,"videoOffsetSeconds":1466,"viewCount":5},"cursor":null},{"node":{"durationSeconds":9,"videoOffsetSeconds":1495,"viewCount":3},"cursor":null},{"node":{"durationSeconds":28,"videoOffsetSeconds":1498,"viewCount":1},"cursor":null},{"node":{"durationSeconds":30,"videoOffsetSeconds":1658,"viewCount":1},"cursor":null},{"node":{"durationSeconds":30,"videoOffsetSeconds":1686,"viewCount":1},"cursor":null},{"node":{"durationSeconds":30,"videoOffsetSeconds":1694,"viewCount":3},"cursor":null},{"node":{"durationSeconds":30,"videoOffsetSeconds":1696,"viewCount":1},"cursor":null},{"node":{"durationSeconds":26,"videoOffsetSeconds":1748,"viewCount":1},"cursor":null},{"node":{"durationSeconds":26,"videoOffsetSeconds":1748,"viewCount":1},"cursor":null},{"node":{"durationSeconds":26,"videoOffsetSeconds":1748,"viewCount":3},"cursor":null},{"node":{"durationSeconds":26,"videoOffsetSeconds":1768,"viewCount":1},"cursor":null},{"node":{"durationSeconds":28,"videoOffsetSeconds":1774,"viewCount":1},"cursor":null},{"node":{"durationSeconds":28,"videoOffsetSeconds":1776,"viewCount":1},"cursor":null},{"node":{"durationSeconds":30,"videoOffsetSeconds":1786,"viewCount":5},"cursor":null},{"node":{"durationSeconds":30,"videoOffsetSeconds":1790,"viewCount":1},"cursor":null},{"node":{"durationSeconds":30,"videoOffsetSeconds":1794,"viewCount":1},"cursor":null},{"node":{"durationSeconds":30,"videoOffsetSeconds":1804,"viewCount":1},"cursor":null},{"node":{"durationSeconds":26,"videoOffsetSeconds":1932,"viewCount":1},"cursor":null},{"node":{"durationSeconds":30,"videoOffsetSeconds":1946,"viewCount":1},"cursor":null},{"node":{"durationSeconds":30,"videoOffsetSeconds":1948,"viewCount":1},"cursor":null},{"node":{"durationSeconds":30,"videoOffsetSeconds":1974,"viewCount":1},"cursor":null},{"node":{"durationSeconds":30,"videoOffsetSeconds":2032,"viewCount":1},"cursor":null},{"node":{"durationSeconds":26,"videoOffsetSeconds":2034,"viewCount":1},"cursor":null},{"node":{"durationSeconds":30,"videoOffsetSeconds":2098,"viewCount":1},"cursor":null},{"node":{"durationSeconds":26,"videoOffsetSeconds":2134,"viewCount":3},"cursor":null},{"node":{"durationSeconds":26,"videoOffsetSeconds":2148,"viewCount":1},"cursor":null},{"node":{"durationSeconds":26,"videoOffsetSeconds":2156,"viewCount":3},"cursor":null},{"node":{"durationSeconds":26,"videoOffsetSeconds":2172,"viewCount":1},"cursor":null},{"node":{"durationSeconds":30,"videoOffsetSeconds":2190,"viewCount":1},"cursor":null},{"node":{"durationSeconds":30,"videoOffsetSeconds":2310,"viewCount":1},"cursor":null},{"node":{"durationSeconds":30,"videoOffsetSeconds":2372,"viewCount":1},"cursor":null},{"node":{"durationSeconds":26,"videoOffsetSeconds":2418,"viewCount":3},"cursor":null},{"node":{"durationSeconds":30,"videoOffsetSeconds":2498,"viewCount":1},"cursor":null},{"node":{"durationSeconds":30,"videoOffsetSeconds":2540,"viewCount":1},"cursor":null},{"node":{"durationSeconds":30,"videoOffsetSeconds":2544,"viewCount":1},"cursor":null},{"node":{"durationSeconds":26,"videoOffsetSeconds":2630,"viewCount":9},"cursor":null},{"node":{"durationSeconds":28,"videoOffsetSeconds":2668,"viewCount":1},"cursor":null},{"node":{"durationSeconds":30,"videoOffsetSeconds":2670,"viewCount":1},"cursor":null},{"node":{"durationSeconds":30,"videoOffsetSeconds":2728,"viewCount":1},"cursor":null},{"node":{"durationSeconds":30,"videoOffsetSeconds":2800,"viewCount":1},"cursor":null},{"node":{"durationSeconds":30,"videoOffsetSeconds":2806,"viewCount":1},"cursor":null},{"node":{"durationSeconds":26,"videoOffsetSeconds":2808,"viewCount":43},"cursor":null},{"node":{"durationSeconds":30,"videoOffsetSeconds":2948,"viewCount":5},"cursor":null},{"node":{"durationSeconds":11,"videoOffsetSeconds":3005,"viewCount":5},"cursor":null},{"node":{"durationSeconds":56,"videoOffsetSeconds":3013,"viewCount":5},"cursor":null},{"node":{"durationSeconds":28,"videoOffsetSeconds":3042,"viewCount":1},"cursor":null},{"node":{"durationSeconds":28,"videoOffsetSeconds":3042,"viewCount":1},"cursor":null},{"node":{"durationSeconds":26,"videoOffsetSeconds":3072,"viewCount":1},"cursor":null},{"node":{"durationSeconds":55,"videoOffsetSeconds":3085,"viewCount":3},"cursor":null},{"node":{"durationSeconds":30,"videoOffsetSeconds":3129,"viewCount":3},"cursor":null},{"node":{"durationSeconds":30,"videoOffsetSeconds":3190,"viewCount":1},"cursor":null},{"node":{"durationSeconds":30,"videoOffsetSeconds":3202,"viewCount":1},"cursor":null},{"node":{"durationSeconds":59,"videoOffsetSeconds":3202,"viewCount":5},"cursor":null},{"node":{"durationSeconds":59,"videoOffsetSeconds":3258,"viewCount":15},"cursor":null},{"node":{"durationSeconds":60,"videoOffsetSeconds":3312,"viewCount":5},"cursor":null},{"node":{"durationSeconds":30,"videoOffsetSeconds":3338,"viewCount":1},"cursor":null},{"node":{"durationSeconds":12,"videoOffsetSeconds":3401,"viewCount":7},"cursor":null},{"node":{"durationSeconds":30,"videoOffsetSeconds":3414,"viewCount":5},"cursor":null},{"node":{"durationSeconds":30,"videoOffsetSeconds":3560,"viewCount":1},"cursor":"eyJTbHVnIjoiRW5jaGFudGluZ0Vhc3lPd2xSaXR6TWl0ei1IY3lvRWpVN2ViWHJINzlNIiwiVm9kSWQiOiIxNTIzNjM5MjM5IiwiQ2xpcE1lZGlhT2Zmc2V0IjozNTYwfQ=="},{"node":{"durationSeconds":28,"videoOffsetSeconds":3606,"viewCount":11},"cursor":null},{"node":{"durationSeconds":28,"videoOffsetSeconds":3626,"viewCount":3},"cursor":null},{"node":{"durationSeconds":30,"videoOffsetSeconds":3680,"viewCount":1},"cursor":null},{"node":{"durationSeconds":20,"videoOffsetSeconds":3699,"viewCount":17},"cursor":null},{"node":{"durationSeconds":30,"videoOffsetSeconds":3700,"viewCount":1},"cursor":null},{"node":{"durationSeconds":30,"videoOffsetSeconds":3718,"viewCount":1},"cursor":null},{"node":{"durationSeconds":30,"videoOffsetSeconds":3730,"viewCount":1},"cursor":null},{"node":{"durationSeconds":28,"videoOffsetSeconds":3776,"viewCount":1},"cursor":null},{"node":{"durationSeconds":30,"videoOffsetSeconds":3782,"viewCount":3},"cursor":null},{"node":{"durationSeconds":28,"videoOffsetSeconds":3796,"viewCount":7},"cursor":null},{"node":{"durationSeconds":26,"videoOffsetSeconds":3856,"viewCount":1},"cursor":null},{"node":{"durationSeconds":30,"videoOffsetSeconds":4000,"viewCount":1},"cursor":null},{"node":{"durationSeconds":26,"videoOffsetSeconds":4034,"viewCount":1},"cursor":null},{"node":{"durationSeconds":26,"videoOffsetSeconds":4042,"viewCount":1},"cursor":null},{"node":{"durationSeconds":28,"videoOffsetSeconds":4046,"viewCount":3},"cursor":null},{"node":{"durationSeconds":30,"videoOffsetSeconds":4084,"viewCount":1},"cursor":null},{"node":{"durationSeconds":30,"videoOffsetSeconds":4086,"viewCount":1},"cursor":null},{"node":{"durationSeconds":30,"videoOffsetSeconds":4170,"viewCount":1},"cursor":null},{"node":{"durationSeconds":30,"videoOffsetSeconds":4312,"viewCount":1},"cursor":null},{"node":{"durationSeconds":26,"videoOffsetSeconds":4314,"viewCount":1},"cursor":null},{"node":{"durationSeconds":30,"videoOffsetSeconds":4318,"viewCount":1},"cursor":null},{"node":{"durationSeconds":30,"videoOffsetSeconds":4328,"viewCount":1},"cursor":null},{"node":{"durationSeconds":30,"videoOffsetSeconds":4340,"viewCount":1},"cursor":null},{"node":{"durationSeconds":26,"videoOffsetSeconds":4340,"viewCount":1},"cursor":null},{"node":{"durationSeconds":26,"videoOffsetSeconds":4366,"viewCount":3},"cursor":null},{"node":{"durationSeconds":26,"videoOffsetSeconds":4368,"viewCount":3},"cursor":null},{"node":{"durationSeconds":28,"videoOffsetSeconds":4432,"viewCount":3},"cursor":null},{"node":{"durationSeconds":30,"videoOffsetSeconds":4532,"viewCount":1},"cursor":null},{"node":{"durationSeconds":28,"videoOffsetSeconds":4596,"viewCount":1},"cursor":null},{"node":{"durationSeconds":26,"videoOffsetSeconds":4612,"viewCount":1},"cursor":null},{"node":{"durationSeconds":28,"videoOffsetSeconds":4632,"viewCount":1},"cursor":null},{"node":{"durationSeconds":28,"videoOffsetSeconds":4642,"viewCount":1},"cursor":null},{"node":{"durationSeconds":26,"videoOffsetSeconds":4660,"viewCount":1},"cursor":null},{"node":{"durationSeconds":28,"videoOffsetSeconds":4718,"viewCount":7},"cursor":null},{"node":{"durationSeconds":30,"videoOffsetSeconds":4760,"viewCount":1},"cursor":null},{"node":{"durationSeconds":30,"videoOffsetSeconds":4762,"viewCount":1},"cursor":null},{"node":{"durationSeconds":30,"videoOffsetSeconds":4780,"viewCount":1},"cursor":null},{"node":{"durationSeconds":26,"videoOffsetSeconds":4802,"viewCount":1},"cursor":null},{"node":{"durationSeconds":26,"videoOffsetSeconds":5000,"viewCount":3},"cursor":null},{"node":{"durationSeconds":30,"videoOffsetSeconds":5130,"viewCount":1},"cursor":null},{"node":{"durationSeconds":30,"videoOffsetSeconds":5130,"viewCount":5},"cursor":null},{"node":{"durationSeconds":30,"videoOffsetSeconds":5140,"viewCount":1},"cursor":null},{"node":{"durationSeconds":5,"videoOffsetSeconds":5174,"viewCount":5},"cursor":null},{"node":{"durationSeconds":5,"videoOffsetSeconds":5174,"viewCount":3},"cursor":null},{"node":{"durationSeconds":4,"videoOffsetSeconds":5177,"viewCount":11},"cursor":null},{"node":{"durationSeconds":26,"videoOffsetSeconds":5182,"viewCount":1},"cursor":null},{"node":{"durationSeconds":26,"videoOffsetSeconds":5182,"viewCount":1},"cursor":null},{"node":{"durationSeconds":30,"videoOffsetSeconds":5190,"viewCount":1},"cursor":null},{"node":{"durationSeconds":30,"videoOffsetSeconds":5270,"viewCount":5},"cursor":null},{"node":{"durationSeconds":26,"videoOffsetSeconds":5278,"viewCount":5},"cursor":null},{"node":{"durationSeconds":26,"videoOffsetSeconds":5286,"viewCount":3},"cursor":null},{"node":{"durationSeconds":30,"videoOffsetSeconds":5290,"viewCount":1},"cursor":null},{"node":{"durationSeconds":30,"videoOffsetSeconds":5290,"viewCount":1},"cursor":null},{"node":{"durationSeconds":30,"videoOffsetSeconds":5290,"viewCount":1},"cursor":null},{"node":{"durationSeconds":30,"videoOffsetSeconds":5310,"viewCount":3},"cursor":null},{"node":{"durationSeconds":30,"videoOffsetSeconds":5482,"viewCount":1},"cursor":null},{"node":{"durationSeconds":26,"videoOffsetSeconds":5498,"viewCount":3},"cursor":null},{"node":{"durationSeconds":12,"videoOffsetSeconds":5503,"viewCount":9},"cursor":null},{"node":{"durationSeconds":30,"videoOffsetSeconds":5510,"viewCount":1},"cursor":null},{"node":{"durationSeconds":30,"videoOffsetSeconds":5526,"viewCount":1},"cursor":null},{"node":{"durationSeconds":30,"videoOffsetSeconds":5540,"viewCount":1},"cursor":null},{"node":{"durationSeconds":30,"videoOffsetSeconds":5540,"viewCount":5},"cursor":null},{"node":{"durationSeconds":30,"videoOffsetSeconds":5550,"viewCount":15},"cursor":null},{"node":{"durationSeconds":26,"videoOffsetSeconds":5624,"viewCount":1},"cursor":null},{"node":{"durationSeconds":30,"videoOffsetSeconds":5710,"viewCount":3},"cursor":null},{"node":{"durationSeconds":30,"videoOffsetSeconds":5740,"viewCount":3},"cursor":null},{"node":{"durationSeconds":30,"videoOffsetSeconds":5750,"viewCount":1},"cursor":null},{"node":{"durationSeconds":30,"videoOffsetSeconds":5810,"viewCount":25},"cursor":null},{"node":{"durationSeconds":28,"videoOffsetSeconds":5872,"viewCount":3},"cursor":null},{"node":{"durationSeconds":30,"videoOffsetSeconds":5880,"viewCount":1},"cursor":null},{"node":{"durationSeconds":26,"videoOffsetSeconds":5896,"viewCount":1},"cursor":null},{"node":{"durationSeconds":30,"videoOffsetSeconds":5944,"viewCount":1},"cursor":null},{"node":{"durationSeconds":30,"videoOffsetSeconds":5950,"viewCount":1},"cursor":null},{"node":{"durationSeconds":30,"videoOffsetSeconds":5956,"viewCount":1},"cursor":null},{"node":{"durationSeconds":30,"videoOffsetSeconds":6026,"viewCount":5},"cursor":null},{"node":{"durationSeconds":28,"videoOffsetSeconds":6062,"viewCount":37},"cursor":null},{"node":{"durationSeconds":30,"videoOffsetSeconds":6150,"viewCount":1},"cursor":null},{"node":{"durationSeconds":26,"videoOffsetSeconds":6204,"viewCount":1},"cursor":null},{"node":{"durationSeconds":30,"videoOffsetSeconds":6240,"viewCount":11},"cursor":null},{"node":{"durationSeconds":26,"videoOffsetSeconds":6358,"viewCount":1},"cursor":null},{"node":{"durationSeconds":30,"videoOffsetSeconds":6380,"viewCount":15},"cursor":null},{"node":{"durationSeconds":26,"videoOffsetSeconds":6436,"viewCount":3},"cursor":null},{"node":{"durationSeconds":28,"videoOffsetSeconds":6546,"viewCount":11},"cursor":null},{"node":{"durationSeconds":30,"videoOffsetSeconds":6576,"viewCount":1},"cursor":null},{"node":{"durationSeconds":28,"videoOffsetSeconds":6630,"viewCount":7},"cursor":null},{"node":{"durationSeconds":30,"videoOffsetSeconds":6632,"viewCount":3},"cursor":null},{"node":{"durationSeconds":30,"videoOffsetSeconds":6638,"viewCount":1},"cursor":null},{"node":{"durationSeconds":30,"videoOffsetSeconds":6642,"viewCount":3},"cursor":null},{"node":{"durationSeconds":26,"videoOffsetSeconds":6646,"viewCount":1},"cursor":null},{"node":{"durationSeconds":26,"videoOffsetSeconds":6646,"viewCount":1},"cursor":null},{"node":{"durationSeconds":14,"videoOffsetSeconds":6651,"viewCount":273},"cursor":null},{"node":{"durationSeconds":30,"videoOffsetSeconds":6654,"viewCount":1},"cursor":null},{"node":{"durationSeconds":28,"videoOffsetSeconds":6664,"viewCount":9},"cursor":null},{"node":{"durationSeconds":30,"videoOffsetSeconds":6728,"viewCount":3},"cursor":null},{"node":{"durationSeconds":30,"videoOffsetSeconds":6752,"viewCount":3},"cursor":null},{"node":{"durationSeconds":28,"videoOffsetSeconds":6756,"viewCount":1},"cursor":null},{"node":{"durationSeconds":30,"videoOffsetSeconds":6810,"viewCount":1},"cursor":null},{"node":{"durationSeconds":30,"videoOffsetSeconds":6828,"viewCount":1},"cursor":null},{"node":{"durationSeconds":30,"videoOffsetSeconds":6864,"viewCount":1},"cursor":null},{"node":{"durationSeconds":30,"videoOffsetSeconds":6908,"viewCount":1},"cursor":"eyJTbHVnIjoiSW1wb3J0YW50Qm94eUJhbmFuYUJyYWluU2x1Zy1fMVBRZVloRnJPV05OdWpPIiwiVm9kSWQiOiIxNTIzNjM5MjM5IiwiQ2xpcE1lZGlhT2Zmc2V0Ijo2OTA4fQ=="},{"node":{"durationSeconds":30,"videoOffsetSeconds":6968,"viewCount":1},"cursor":null},{"node":{"durationSeconds":26,"videoOffsetSeconds":6970,"viewCount":3},"cursor":null},{"node":{"durationSeconds":16,"videoOffsetSeconds":7008,"viewCount":7},"cursor":null},{"node":{"durationSeconds":11,"videoOffsetSeconds":7046,"viewCount":3},"cursor":null},{"node":{"durationSeconds":26,"videoOffsetSeconds":7186,"viewCount":1},"cursor":null},{"node":{"durationSeconds":30,"videoOffsetSeconds":7202,"viewCount":1},"cursor":null},{"node":{"durationSeconds":28,"videoOffsetSeconds":7304,"viewCount":1},"cursor":null},{"node":{"durationSeconds":28,"videoOffsetSeconds":7320,"viewCount":1},"cursor":null},{"node":{"durationSeconds":30,"videoOffsetSeconds":7490,"viewCount":1},"cursor":null},{"node":{"durationSeconds":30,"videoOffsetSeconds":7510,"viewCount":1},"cursor":null},{"node":{"durationSeconds":28,"videoOffsetSeconds":7704,"viewCount":1},"cursor":null},{"node":{"durationSeconds":28,"videoOffsetSeconds":7704,"viewCount":1},"cursor":null},{"node":{"durationSeconds":30,"videoOffsetSeconds":7754,"viewCount":1},"cursor":null},{"node":{"durationSeconds":30,"videoOffsetSeconds":7790,"viewCount":1},"cursor":null},{"node":{"durationSeconds":30,"videoOffsetSeconds":7800,"viewCount":1},"cursor":null},{"node":{"durationSeconds":30,"videoOffsetSeconds":7818,"viewCount":1},"cursor":null},{"node":{"durationSeconds":28,"videoOffsetSeconds":7878,"viewCount":3},"cursor":null},{"node":{"durationSeconds":30,"videoOffsetSeconds":8068,"viewCount":1},"cursor":null},{"node":{"durationSeconds":30,"videoOffsetSeconds":8084,"viewCount":1},"cursor":null},{"node":{"durationSeconds":30,"videoOffsetSeconds":8126,"viewCount":1},"cursor":null},{"node":{"durationSeconds":30,"videoOffsetSeconds":8214,"viewCount":1},"cursor":null},{"node":{"durationSeconds":26,"videoOffsetSeconds":8228,"viewCount":1},"cursor":null},{"node":{"durationSeconds":30,"videoOffsetSeconds":8368,"viewCount":1},"cursor":null},{"node":{"durationSeconds":30,"videoOffsetSeconds":8380,"viewCount":1},"cursor":null},{"node":{"durationSeconds":30,"videoOffsetSeconds":8512,"viewCount":11},"cursor":null},{"node":{"durationSeconds":26,"videoOffsetSeconds":8688,"viewCount":1},"cursor":null},{"node":{"durationSeconds":30,"videoOffsetSeconds":8788,"viewCount":1},"cursor":null},{"node":{"durationSeconds":30,"videoOffsetSeconds":8894,"viewCount":61},"cursor":null},{"node":{"durationSeconds":30,"videoOffsetSeconds":8914,"viewCount":1},"cursor":null},{"node":{"durationSeconds":20,"videoOffsetSeconds":8925,"viewCount":5},"cursor":null},{"node":{"durationSeconds":26,"videoOffsetSeconds":8928,"viewCount":3},"cursor":null},{"node":{"durationSeconds":30,"videoOffsetSeconds":8932,"viewCount":17},"cursor":null},{"node":{"durationSeconds":28,"videoOffsetSeconds":8934,"viewCount":1},"cursor":null},{"node":{"durationSeconds":28,"videoOffsetSeconds":8936,"viewCount":1},"cursor":null},{"node":{"durationSeconds":30,"videoOffsetSeconds":8940,"viewCount":1},"cursor":null},{"node":{"durationSeconds":28,"videoOffsetSeconds":8946,"viewCount":1},"cursor":null},{"node":{"durationSeconds":28,"videoOffsetSeconds":8958,"viewCount":1},"cursor":null},{"node":{"durationSeconds":30,"videoOffsetSeconds":8966,"viewCount":1},"cursor":null},{"node":{"durationSeconds":30,"videoOffsetSeconds":9186,"viewCount":1},"cursor":null},{"node":{"durationSeconds":30,"videoOffsetSeconds":9222,"viewCount":1},"cursor":null},{"node":{"durationSeconds":28,"videoOffsetSeconds":9232,"viewCount":3},"cursor":null},{"node":{"durationSeconds":30,"videoOffsetSeconds":9234,"viewCount":1},"cursor":null},{"node":{"durationSeconds":30,"videoOffsetSeconds":9252,"viewCount":1},"cursor":null},{"node":{"durationSeconds":28,"videoOffsetSeconds":9482,"viewCount":1},"cursor":null},{"node":{"durationSeconds":26,"videoOffsetSeconds":9504,"viewCount":1},"cursor":null},{"node":{"durationSeconds":26,"videoOffsetSeconds":9671,"viewCount":15},"cursor":null},{"node":{"durationSeconds":9,"videoOffsetSeconds":9680,"viewCount":5},"cursor":null},{"node":{"durationSeconds":28,"videoOffsetSeconds":9734,"viewCount":3},"cursor":null},{"node":{"durationSeconds":26,"videoOffsetSeconds":9738,"viewCount":3},"cursor":null},{"node":{"durationSeconds":30,"videoOffsetSeconds":9846,"viewCount":1},"cursor":null},{"node":{"durationSeconds":30,"videoOffsetSeconds":9852,"viewCount":1},"cursor":null},{"node":{"durationSeconds":28,"videoOffsetSeconds":9910,"viewCount":3},"cursor":null},{"node":{"durationSeconds":26,"videoOffsetSeconds":9936,"viewCount":1},"cursor":null},{"node":{"durationSeconds":30,"videoOffsetSeconds":10054,"viewCount":1},"cursor":null},{"node":{"durationSeconds":30,"videoOffsetSeconds":10152,"viewCount":1},"cursor":null},{"node":{"durationSeconds":30,"videoOffsetSeconds":10252,"viewCount":1},"cursor":null},{"node":{"durationSeconds":30,"videoOffsetSeconds":10524,"viewCount":1},"cursor":null},{"node":{"durationSeconds":30,"videoOffsetSeconds":10536,"viewCount":1},"cursor":null},{"node":{"durationSeconds":28,"videoOffsetSeconds":10778,"viewCount":1},"cursor":null},{"node":{"durationSeconds":30,"videoOffsetSeconds":10800,"viewCount":1},"cursor":null},{"node":{"durationSeconds":30,"videoOffsetSeconds":10926,"viewCount":1},"cursor":null},{"node":{"durationSeconds":30,"videoOffsetSeconds":10996,"viewCount":3},"cursor":null},{"node":{"durationSeconds":28,"videoOffsetSeconds":11024,"viewCount":1},"cursor":null},{"node":{"durationSeconds":28,"videoOffsetSeconds":11372,"viewCount":1},"cursor":null},{"node":{"durationSeconds":30,"videoOffsetSeconds":11448,"viewCount":1},"cursor":null},{"node":{"durationSeconds":26,"videoOffsetSeconds":11532,"viewCount":1},"cursor":null},{"node":{"durationSeconds":26,"videoOffsetSeconds":11532,"viewCount":1},"cursor":null},{"node":{"durationSeconds":26,"videoOffsetSeconds":11532,"viewCount":1},"cursor":null},{"node":{"durationSeconds":28,"videoOffsetSeconds":11534,"viewCount":1},"cursor":null},{"node":{"durationSeconds":26,"videoOffsetSeconds":11700,"viewCount":1},"cursor":null},{"node":{"durationSeconds":30,"videoOffsetSeconds":11714,"viewCount":1},"cursor":null},{"node":{"durationSeconds":30,"videoOffsetSeconds":11858,"viewCount":1},"cursor":null},{"node":{"durationSeconds":30,"videoOffsetSeconds":11918,"viewCount":1},"cursor":null},{"node":{"durationSeconds":28,"videoOffsetSeconds":12172,"viewCount":1},"cursor":null},{"node":{"durationSeconds":28,"videoOffsetSeconds":12214,"viewCount":1},"cursor":null},{"node":{"durationSeconds":30,"videoOffsetSeconds":12292,"viewCount":1},"cursor":null},{"node":{"durationSeconds":30,"videoOffsetSeconds":12294,"viewCount":1},"cursor":null},{"node":{"durationSeconds":30,"videoOffsetSeconds":12356,"viewCount":1},"cursor":null},{"node":{"durationSeconds":30,"videoOffsetSeconds":12464,"viewCount":1},"cursor":null},{"node":{"durationSeconds":30,"videoOffsetSeconds":12510,"viewCount":1},"cursor":null},{"node":{"durationSeconds":30,"videoOffsetSeconds":12620,"viewCount":1},"cursor":null},{"node":{"durationSeconds":30,"videoOffsetSeconds":12656,"viewCount":1},"cursor":null},{"node":{"durationSeconds":30,"videoOffsetSeconds":12834,"viewCount":1},"cursor":null},{"node":{"durationSeconds":30,"videoOffsetSeconds":12878,"viewCount":1},"cursor":null},{"node":{"durationSeconds":26,"videoOffsetSeconds":12994,"viewCount":1},"cursor":null},{"node":{"durationSeconds":26,"videoOffsetSeconds":13122,"viewCount":5},"cursor":null},{"node":{"durationSeconds":30,"videoOffsetSeconds":13130,"viewCount":1},"cursor":null},{"node":{"durationSeconds":30,"videoOffsetSeconds":13132,"viewCount":1},"cursor":null},{"node":{"durationSeconds":26,"videoOffsetSeconds":13462,"viewCount":1},"cursor":null},{"node":{"durationSeconds":30,"videoOffsetSeconds":13500,"viewCount":1},"cursor":null},{"node":{"durationSeconds":30,"videoOffsetSeconds":13538,"viewCount":1},"cursor":null},{"node":{"durationSeconds":30,"videoOffsetSeconds":13548,"viewCount":1},"cursor":null},{"node":{"durationSeconds":30,"videoOffsetSeconds":13590,"viewCount":1},"cursor":null},{"node":{"durationSeconds":28,"videoOffsetSeconds":13610,"viewCount":1},"cursor":null},{"node":{"durationSeconds":26,"videoOffsetSeconds":13692,"viewCount":1},"cursor":null},{"node":{"durationSeconds":26,"videoOffsetSeconds":13794,"viewCount":1},"cursor":null},{"node":{"durationSeconds":26,"videoOffsetSeconds":13812,"viewCount":1},"cursor":null},{"node":{"durationSeconds":30,"videoOffsetSeconds":13820,"viewCount":1},"cursor":null},{"node":{"durationSeconds":26,"videoOffsetSeconds":13952,"viewCount":1},"cursor":null},{"node":{"durationSeconds":30,"videoOffsetSeconds":13992,"viewCount":1},"cursor":"eyJTbHVnIjoiQm9tYmFzdGljVGFuZ2libGVFbGVwaGFudEVsZUdpZ2dsZS1DMnloX0Nfdjhja3lMY2xqIiwiVm9kSWQiOiIxNTIzNjM5MjM5IiwiQ2xpcE1lZGlhT2Zmc2V0IjoxMzk5Mn0="},{"node":{"durationSeconds":30,"videoOffsetSeconds":14056,"viewCount":1},"cursor":null},{"node":{"durationSeconds":26,"videoOffsetSeconds":14090,"viewCount":1},"cursor":null},{"node":{"durationSeconds":30,"videoOffsetSeconds":14192,"viewCount":1},"cursor":null},{"node":{"durationSeconds":26,"videoOffsetSeconds":14276,"viewCount":1},"cursor":null},{"node":{"durationSeconds":30,"videoOffsetSeconds":14290,"viewCount":3},"cursor":null},{"node":{"durationSeconds":30,"videoOffsetSeconds":14308,"viewCount":1},"cursor":null},{"node":{"durationSeconds":30,"videoOffsetSeconds":14340,"viewCount":1},"cursor":null},{"node":{"durationSeconds":28,"videoOffsetSeconds":14342,"viewCount":1},"cursor":null},{"node":{"durationSeconds":30,"videoOffsetSeconds":14468,"viewCount":1},"cursor":null},{"node":{"durationSeconds":30,"videoOffsetSeconds":14650,"viewCount":1},"cursor":null},{"node":{"durationSeconds":26,"videoOffsetSeconds":14690,"viewCount":1},"cursor":null},{"node":{"durationSeconds":30,"videoOffsetSeconds":14848,"viewCount":1},"cursor":null},{"node":{"durationSeconds":26,"videoOffsetSeconds":14864,"viewCount":5},"cursor":null},{"node":{"durationSeconds":30,"videoOffsetSeconds":14922,"viewCount":1},"cursor":null},{"node":{"durationSeconds":26,"videoOffsetSeconds":14926,"viewCount":1},"cursor":null},{"node":{"durationSeconds":26,"videoOffsetSeconds":14926,"viewCount":7},"cursor":null},{"node":{"durationSeconds":30,"videoOffsetSeconds":14972,"viewCount":1},"cursor":null},{"node":{"durationSeconds":30,"videoOffsetSeconds":15066,"viewCount":1},"cursor":null},{"node":{"durationSeconds":30,"videoOffsetSeconds":15226,"viewCount":1},"cursor":null},{"node":{"durationSeconds":26,"videoOffsetSeconds":15278,"viewCount":29},"cursor":null},{"node":{"durationSeconds":26,"videoOffsetSeconds":15278,"viewCount":3},"cursor":null},{"node":{"durationSeconds":26,"videoOffsetSeconds":15284,"viewCount":1},"cursor":null},{"node":{"durationSeconds":26,"videoOffsetSeconds":15288,"viewCount":1},"cursor":null},{"node":{"durationSeconds":26,"videoOffsetSeconds":15296,"viewCount":3},"cursor":null},{"node":{"durationSeconds":26,"videoOffsetSeconds":15352,"viewCount":1},"cursor":null},{"node":{"durationSeconds":26,"videoOffsetSeconds":15356,"viewCount":1},"cursor":null},{"node":{"durationSeconds":26,"videoOffsetSeconds":15356,"viewCount":1},"cursor":null},{"node":{"durationSeconds":26,"videoOffsetSeconds":15366,"viewCount":1},"cursor":null},{"node":{"durationSeconds":18,"videoOffsetSeconds":15371,"viewCount":5},"cursor":null},{"node":{"durationSeconds":26,"videoOffsetSeconds":15376,"viewCount":1},"cursor":null},{"node":{"durationSeconds":30,"videoOffsetSeconds":15411,"viewCount":1},"cursor":null},{"node":{"durationSeconds":26,"videoOffsetSeconds":15422,"viewCount":1},"cursor":null},{"node":{"durationSeconds":26,"videoOffsetSeconds":15430,"viewCount":1},"cursor":null},{"node":{"durationSeconds":30,"videoOffsetSeconds":15454,"viewCount":3},"cursor":null},{"node":{"durationSeconds":30,"videoOffsetSeconds":15512,"viewCount":1},"cursor":null},{"node":{"durationSeconds":26,"videoOffsetSeconds":15540,"viewCount":1},"cursor":null},{"node":{"durationSeconds":12,"videoOffsetSeconds":15584,"viewCount":5},"cursor":null},{"node":{"durationSeconds":30,"videoOffsetSeconds":15610,"viewCount":1},"cursor":null},{"node":{"durationSeconds":30,"videoOffsetSeconds":15616,"viewCount":1},"cursor":null},{"node":{"durationSeconds":30,"videoOffsetSeconds":15646,"viewCount":1},"cursor":null},{"node":{"durationSeconds":30,"videoOffsetSeconds":15660,"viewCount":1},"cursor":null},{"node":{"durationSeconds":28,"videoOffsetSeconds":15708,"viewCount":1},"cursor":null},{"node":{"durationSeconds":30,"videoOffsetSeconds":15718,"viewCount":1},"cursor":null},{"node":{"durationSeconds":30,"videoOffsetSeconds":15760,"viewCount":1},"cursor":null},{"node":{"durationSeconds":30,"videoOffsetSeconds":15938,"viewCount":1},"cursor":null},{"node":{"durationSeconds":30,"videoOffsetSeconds":15950,"viewCount":1},"cursor":null},{"node":{"durationSeconds":30,"videoOffsetSeconds":15952,"viewCount":1},"cursor":null},{"node":{"durationSeconds":30,"videoOffsetSeconds":15952,"viewCount":5},"cursor":null},{"node":{"durationSeconds":30,"videoOffsetSeconds":15974,"viewCount":1},"cursor":null},{"node":{"durationSeconds":30,"videoOffsetSeconds":16096,"viewCount":1},"cursor":null},{"node":{"durationSeconds":28,"videoOffsetSeconds":16146,"viewCount":1},"cursor":null},{"node":{"durationSeconds":30,"videoOffsetSeconds":16186,"viewCount":1},"cursor":null},{"node":{"durationSeconds":30,"videoOffsetSeconds":16194,"viewCount":1},"cursor":null},{"node":{"durationSeconds":30,"videoOffsetSeconds":16200,"viewCount":1},"cursor":null},{"node":{"durationSeconds":26,"videoOffsetSeconds":16226,"viewCount":3},"cursor":null},{"node":{"durationSeconds":30,"videoOffsetSeconds":16258,"viewCount":1},"cursor":null},{"node":{"durationSeconds":26,"videoOffsetSeconds":16366,"viewCount":5},"cursor":null},{"node":{"durationSeconds":26,"videoOffsetSeconds":16410,"viewCount":1},"cursor":null},{"node":{"durationSeconds":26,"videoOffsetSeconds":16416,"viewCount":1},"cursor":null},{"node":{"durationSeconds":30,"videoOffsetSeconds":16460,"viewCount":1},"cursor":null},{"node":{"durationSeconds":30,"videoOffsetSeconds":16470,"viewCount":1},"cursor":null},{"node":{"durationSeconds":30,"videoOffsetSeconds":16498,"viewCount":1},"cursor":null},{"node":{"durationSeconds":26,"videoOffsetSeconds":16512,"viewCount":1},"cursor":null},{"node":{"durationSeconds":26,"videoOffsetSeconds":16512,"viewCount":5},"cursor":null},{"node":{"durationSeconds":26,"videoOffsetSeconds":16514,"viewCount":7},"cursor":null},{"node":{"durationSeconds":28,"videoOffsetSeconds":16518,"viewCount":7},"cursor":null},{"node":{"durationSeconds":28,"videoOffsetSeconds":16518,"viewCount":1},"cursor":null},{"node":{"durationSeconds":26,"videoOffsetSeconds":16538,"viewCount":1},"cursor":null},{"node":{"durationSeconds":28,"videoOffsetSeconds":16566,"viewCount":1},"cursor":null},{"node":{"durationSeconds":26,"videoOffsetSeconds":16616,"viewCount":1},"cursor":null},{"node":{"durationSeconds":28,"videoOffsetSeconds":16756,"viewCount":1},"cursor":null},{"node":{"durationSeconds":28,"videoOffsetSeconds":16944,"viewCount":3},"cursor":null},{"node":{"durationSeconds":30,"videoOffsetSeconds":16972,"viewCount":1},"cursor":null},{"node":{"durationSeconds":30,"videoOffsetSeconds":16980,"viewCount":1},"cursor":null},{"node":{"durationSeconds":30,"videoOffsetSeconds":16990,"viewCount":1},"cursor":null},{"node":{"durationSeconds":30,"videoOffsetSeconds":16994,"viewCount":1},"cursor":null},{"node":{"durationSeconds":30,"videoOffsetSeconds":17008,"viewCount":1},"cursor":null},{"node":{"durationSeconds":14,"videoOffsetSeconds":17013,"viewCount":3},"cursor":null},{"node":{"durationSeconds":26,"videoOffsetSeconds":17066,"viewCount":9},"cursor":null},{"node":{"durationSeconds":28,"videoOffsetSeconds":17124,"viewCount":3},"cursor":null},{"node":{"durationSeconds":30,"videoOffsetSeconds":17164,"viewCount":1},"cursor":null},{"node":{"durationSeconds":30,"videoOffsetSeconds":17342,"viewCount":1},"cursor":null},{"node":{"durationSeconds":6,"videoOffsetSeconds":17383,"viewCount":1},"cursor":null},{"node":{"durationSeconds":28,"videoOffsetSeconds":17466,"viewCount":1},"cursor":null},{"node":{"durationSeconds":28,"videoOffsetSeconds":17466,"viewCount":1},"cursor":null},{"node":{"durationSeconds":30,"videoOffsetSeconds":17474,"viewCount":1},"cursor":null},{"node":{"durationSeconds":30,"videoOffsetSeconds":17678,"viewCount":1},"cursor":null},{"node":{"durationSeconds":30,"videoOffsetSeconds":17750,"viewCount":1},"cursor":null},{"node":{"durationSeconds":30,"videoOffsetSeconds":17760,"viewCount":1},"cursor":null},{"node":{"durationSeconds":30,"videoOffsetSeconds":17866,"viewCount":1},"cursor":null},{"node":{"durationSeconds":26,"videoOffsetSeconds":17968,"viewCount":1},"cursor":null},{"node":{"durationSeconds":30,"videoOffsetSeconds":17990,"viewCount":1},"cursor":null},{"node":{"durationSeconds":26,"videoOffsetSeconds":18036,"viewCount":1},"cursor":null},{"node":{"durationSeconds":9,"videoOffsetSeconds":18048,"viewCount":5},"cursor":null},{"node":{"durationSeconds":30,"videoOffsetSeconds":18060,"viewCount":1},"cursor":null},{"node":{"durationSeconds":30,"videoOffsetSeconds":18114,"viewCount":1},"cursor":null},{"node":{"durationSeconds":30,"videoOffsetSeconds":18248,"viewCount":1},"cursor":null},{"node":{"durationSeconds":26,"videoOffsetSeconds":18252,"viewCount":1},"cursor":null},{"node":{"durationSeconds":30,"videoOffsetSeconds":18272,"viewCount":1},"cursor":null},{"node":{"durationSeconds":30,"videoOffsetSeconds":18362,"viewCount":1},"cursor":"eyJTbHVnIjoiQ2FsbURlbGljaW91c09yeXhLaXBwYS1LZlAxMjNkeWpfd3NBYi05IiwiVm9kSWQiOiIxNTIzNjM5MjM5IiwiQ2xpcE1lZGlhT2Zmc2V0IjoxODM2Mn0="},{"node":{"durationSeconds":26,"videoOffsetSeconds":18656,"viewCount":1},"cursor":null},{"node":{"durationSeconds":28,"videoOffsetSeconds":18744,"viewCount":1},"cursor":null},{"node":{"durationSeconds":26,"videoOffsetSeconds":19062,"viewCount":1},"cursor":null},{"node":{"durationSeconds":28,"videoOffsetSeconds":19172,"viewCount":1},"cursor":null},{"node":{"durationSeconds":30,"videoOffsetSeconds":19200,"viewCount":1},"cursor":null},{"node":{"durationSeconds":30,"videoOffsetSeconds":19200,"viewCount":1},"cursor":null},{"node":{"durationSeconds":30,"videoOffsetSeconds":19200,"viewCount":1},"cursor":null},{"node":{"durationSeconds":30,"videoOffsetSeconds":19200,"viewCount":1},"cursor":null},{"node":{"durationSeconds":30,"videoOffsetSeconds":19200,"viewCount":1},"cursor":null},{"node":{"durationSeconds":30,"videoOffsetSeconds":19224,"viewCount":1},"cursor":null},{"node":{"durationSeconds":30,"videoOffsetSeconds":19230,"viewCount":1},"cursor":null},{"node":{"durationSeconds":30,"videoOffsetSeconds":19300,"viewCount":1},"cursor":null},{"node":{"durationSeconds":26,"videoOffsetSeconds":19380,"viewCount":1},"cursor":null},{"node":{"durationSeconds":30,"videoOffsetSeconds":19414,"viewCount":1},"cursor":null},{"node":{"durationSeconds":30,"videoOffsetSeconds":19486,"viewCount":1},"cursor":null},{"node":{"durationSeconds":26,"videoOffsetSeconds":19654,"viewCount":1},"cursor":null},{"node":{"durationSeconds":28,"videoOffsetSeconds":19656,"viewCount":1},"cursor":null},{"node":{"durationSeconds":26,"videoOffsetSeconds":19660,"viewCount":1},"cursor":null},{"node":{"durationSeconds":26,"videoOffsetSeconds":19664,"viewCount":1},"cursor":null},{"node":{"durationSeconds":26,"videoOffsetSeconds":19668,"viewCount":1},"cursor":null},{"node":{"durationSeconds":30,"videoOffsetSeconds":19820,"viewCount":1},"cursor":null},{"node":{"durationSeconds":28,"videoOffsetSeconds":19960,"viewCount":1},"cursor":null},{"node":{"durationSeconds":28,"videoOffsetSeconds":19964,"viewCount":1},"cursor":null},{"node":{"durationSeconds":28,"videoOffsetSeconds":19966,"viewCount":1},"cursor":null},{"node":{"durationSeconds":30,"videoOffsetSeconds":19988,"viewCount":1},"cursor":null},{"node":{"durationSeconds":30,"videoOffsetSeconds":19992,"viewCount":1},"cursor":null},{"node":{"durationSeconds":30,"videoOffsetSeconds":20028,"viewCount":1},"cursor":null},{"node":{"durationSeconds":30,"videoOffsetSeconds":20044,"viewCount":1},"cursor":null},{"node":{"durationSeconds":28,"videoOffsetSeconds":20108,"viewCount":1},"cursor":null},{"node":{"durationSeconds":30,"videoOffsetSeconds":20124,"viewCount":1},"cursor":null},{"node":{"durationSeconds":30,"videoOffsetSeconds":20126,"viewCount":1},"cursor":null},{"node":{"durationSeconds":30,"videoOffsetSeconds":20218,"viewCount":1},"cursor":null},{"node":{"durationSeconds":30,"videoOffsetSeconds":20590,"viewCount":1},"cursor":null},{"node":{"durationSeconds":30,"videoOffsetSeconds":20626,"viewCount":1},"cursor":null},{"node":{"durationSeconds":30,"videoOffsetSeconds":20644,"viewCount":1},"cursor":null},{"node":{"durationSeconds":28,"videoOffsetSeconds":20738,"viewCount":1},"cursor":null},{"node":{"durationSeconds":30,"videoOffsetSeconds":20816,"viewCount":1},"cursor":null},{"node":{"durationSeconds":30,"videoOffsetSeconds":21028,"viewCount":3},"cursor":null},{"node":{"durationSeconds":30,"videoOffsetSeconds":21044,"viewCount":3},"cursor":null},{"node":{"durationSeconds":30,"videoOffsetSeconds":21056,"viewCount":3},"cursor":null},{"node":{"durationSeconds":30,"videoOffsetSeconds":21202,"viewCount":1},"cursor":null},{"node":{"durationSeconds":26,"videoOffsetSeconds":21378,"viewCount":1},"cursor":null},{"node":{"durationSeconds":30,"videoOffsetSeconds":21422,"viewCount":3},"cursor":null},{"node":{"durationSeconds":30,"videoOffsetSeconds":21452,"viewCount":5},"cursor":null},{"node":{"durationSeconds":30,"videoOffsetSeconds":21500,"viewCount":5},"cursor":null},{"node":{"durationSeconds":30,"videoOffsetSeconds":21540,"viewCount":1},"cursor":null}],"url":{"quality":"Audio Only","resolution":null,"url":"https://d2vjef5jvl6bfs.cloudfront.net/d91bfbaf918000612e57_lasapaaaaa_39874264761_1657073378/audio_only/index-dvr.m3u8"},"len":21610}